[
  {
    "title": "Mobile_Suit_Gundam_AGE",
    "id": "10808",
    "url": "https://myanimelist.net/anime/10808/Mobile_Suit_Gundam_AGE",
    "user": "shakeyourpup45",
    "profile": "/profile/shakeyourpup45/reviews",
    "pages": "2",
    "number": "1",
    "link": "/reviews.php?id=61661",
    "jp": "--- | --- | ---\n全体的な|  6\n--- | ---\nストーリー|  6\nアニメーション|\nサウンド|  7\nキャラクター|  6\n|  7\n\n'A story than spans 3 generations for 100 years.' (100年に渡る3世代の物語)\n\nART：ガンダム00をテレビで成功させるためのアニメーションガンダムシリーズであるAGEは、「カラフル」または「幼稚」のキャラクターアートのために、いくつかのネガティブなまつげを受けています。  Naguo Takuzo（ビデオゲームInazuma ElevenとLayton教授）はキャラクターアートを担当しており、Asunoファミリーの深刻な話を尊重しない印象を与えたり、ガンダムに続く一般的な軍事的なジャンル 開口部も見ることができます。 。 私はそのように感じていますが、私は自分のキャラクターが顔を出していると思っていて、鼻はいつか怠け者に見えるのですが、そのスタイルがそのキャラクターを強調してくれると思います。 メカの芸術はいいですし、おもちゃのモデルのブログをチェックするのも楽しいです。  Wing、X、Crossbone、さらには00のような前回のガンダム作品に取り組んでいたデザイナーがいくつかいますが、ガンダムAGE自体は00より多くを採用しているようです。あなたはAGE-1内でExiaを見ることはできません。 スタークラフトを除いて、どこにもCGIはほとんどない。 それは私のプラスです！ あなたは簡単に戦いに従うことができます。 背景技術は、森林や植民地の建物構造のように、よく行われています。\n\nストーリー：AGEは、若手ウォッチャーがガンダムの製品を認識し、幅広い聴衆にアピールするために開発されました。 私は同じ家族のパイロットの約3世代のストーリーラインが素晴らしいアイデアだと思った。 これは、小さな開発時間を持つものを残す。 破壊と暴力が起こる。 また、地球連合や宇宙植民地、家族によって設計された超兵器と戦うために強制された若いガンダムパイロット、そして宇宙船から逃れる軍人や民間人など、これまでのショーとは正反対の特徴を持っています。 より多くのことを説明することは、スポイラーを与えるかもしれませんが、あなたがUCシリーズをよく知っていれば、AGEを見ながらそれらを指摘することができます。 さらに、私はUEがクールな敵だと思う。 彼らの悪質な戦術と連邦政府の無力さは、彼らを見て興味深いものにします。 しかし一方で、ストーリーは非常に線形であり、その支持キャラクターにとって不公平であるという話は否定的です。 ストーリーラインは3世代に分割されているので、時間がすばやく進み、季節が短くなります。 クライマックスはたくさんありますが、シーズンは短いです。\n\nサウンド：素敵な音楽。  OPとEDはロックとポップのミックスです。 私は特にオープニングテーマ「Asu he」と「SHARP」が好きです。  ED「My World」もうまくいっています。 ボイスワイズ、井上和彦（Zガンダム出身のジェリッド、アストレイ出身のガイ）は語り手としてはうまくいきます。 彼の孫に祖父のように、彼のぞっとする音色は、UEによって混沌に投げ込まれた世代の緊張した現実の現実を伝えます。 それと並行して、坂口大輔（勝利ガンダムからのUsso）、宇宙飛行士（Xガンダムの小人）、小野大輔（STARGAZERのSve​​nCal）、宇宙飛行士（Lace of 00）、遠藤綾 、キミ・クロスロード（00）、ロミ・パク（ロラン・Aターン）、諏訪部純一（SEED DESTINY）、草なぎ大仁が登場する。 主人公（江口拓也、豊永俊之、山本一夫）は、若干の新生児派遣によって声が上がりますが、男の子を描くのにはうまくいきます。\n\nキャラクター：私が言ったように、ストーリーはまっすぐです。 主人公は、浅野家の一員として、最も発展しています。 各シーズンはすぐに通り抜け、文字を残して置き換えてから、それらを十分に知るようにします。 これはロマンチックな関係になるとかなり気分が悪くなります。 私を悩ますことの1つは、ガンダムが考慮する力であるため、多くの（すべてではない）サイドキャラクターが多かれ少なかれ重要ではないということです。 また、アンタゴニストは、おそらくは「公平なゴール」で非常に悪質で、何よりも怪物のように見える。\n\nENJOY / OVERALL：物語のシンプルさ、いくつかの文字の悪い方向。 私はAGEの家族概念とガンダムの進化が好きです。 良い音楽。 私はそれが公正なショーだと思うし、ガンダムの本質を持っている。 このショーがあなたに何かを教えてくれたら、怒りや嫌悪感を与えないでください。",
    "notes": "---|---|---\n\n\u001b[1m--- | --- | ---\u001b[22m\n\u001b[1m(-- - | -- - | -- -)\u001b[22m\n\nTranslations of \u001b[4m---|---|---\u001b[24m\n[ \u001b[4mEnglish\u001b[24m -> \u001b[1m日本語\u001b[22m ]\n\n\u001b[4m---|---|---\u001b[24m\n    \u001b[1m--- | --- | ---\u001b[22m\nOverall | 6\n\n\u001b[1m全体的な|  6\u001b[22m\n\u001b[1m(Zentai-tekina | 6)\u001b[22m\n\nTranslations of \u001b[4mOverall | 6\u001b[24m\n[ \u001b[4mEnglish\u001b[24m -> \u001b[1m日本語\u001b[22m ]\n\n\u001b[4mOverall |\u001b[24m\n    \u001b[1m全体的な|\u001b[22m, \u001b[1m総合的な|\u001b[22m\n\u001b[4m6\u001b[24m\n    \u001b[1m6\u001b[22m\n---|---\n\n\u001b[1m--- | ---\u001b[22m\n\u001b[1m(-- - | -- -)\u001b[22m\n\nTranslations of \u001b[4m---|---\u001b[24m\n[ \u001b[4mEnglish\u001b[24m -> \u001b[1m日本語\u001b[22m ]\n\n\u001b[4m---|---\u001b[24m\n    \u001b[1m--- | ---\u001b[22m\nStory | 6\n\n\u001b[1mストーリー|  6\u001b[22m\n\u001b[1m(Sutōrī | 6)\u001b[22m\n\nTranslations of \u001b[4mStory | 6\u001b[24m\n[ \u001b[4mEnglish\u001b[24m -> \u001b[1m日本語\u001b[22m ]\n\n\u001b[4mStory |\u001b[24m\n    \u001b[1mストーリー|\u001b[22m\n\u001b[4m6\u001b[24m\n    \u001b[1m6\u001b[22m\nAnimation |\n\n\u001b[1mアニメーション|\u001b[22m\n\u001b[1m(Animēshon |)\u001b[22m\n\nTranslations of \u001b[4mAnimation |\u001b[24m\n[ \u001b[4mEnglish\u001b[24m -> \u001b[1m日本語\u001b[22m ]\n\n\u001b[4mAnimation |\u001b[24m\n    \u001b[1mアニメーション|\u001b[22m\nSound | 7\n\n\u001b[1mサウンド|  7\u001b[22m\n\u001b[1m(Saundo | 7)\u001b[22m\n\nTranslations of \u001b[4mSound | 7\u001b[24m\n[ \u001b[4mEnglish\u001b[24m -> \u001b[1m日本語\u001b[22m ]\n\n\u001b[4mSound |\u001b[24m\n    \u001b[1mサウンド|\u001b[22m\n\u001b[4m7\u001b[24m\n    \u001b[1m7\u001b[22m\nCharacter | 6\n\n\u001b[1mキャラクター|  6\u001b[22m\n\u001b[1m(Kyarakutā | 6)\u001b[22m\n\nTranslations of \u001b[4mCharacter | 6\u001b[24m\n[ \u001b[4mEnglish\u001b[24m -> \u001b[1m日本語\u001b[22m ]\n\n\u001b[4mCharacter |\u001b[24m\n    \u001b[1mキャラクター|\u001b[22m, \u001b[1m文字|\u001b[22m\n\u001b[4m6\u001b[24m\n    \u001b[1m6\u001b[22m\nEnjoyment | 7\n\n\u001b[1m|  7\u001b[22m\n\u001b[1m(| 7)\u001b[22m\n\nTranslations of \u001b[4mEnjoyment | 7\u001b[24m\n[ \u001b[4mEnglish\u001b[24m -> \u001b[1m日本語\u001b[22m ]\n\n\u001b[4mEnjoyment |\u001b[24m\n    \u001b[1m|\u001b[22m, \u001b[1m楽しさ|\u001b[22m\n\u001b[4m7\u001b[24m\n    \u001b[1m7\u001b[22m\n\u001b[1m\u001b[22m\n'A story than spans 3 generations for 100 years.' (100年に渡る3世代の物語)\n(' A story zan spans 3 generations fō 100 iyāzu.' (100-Nen ni wataru 3 sedai no monogatari))\n\n\u001b[1m'A story than spans 3 generations for 100 years.' (100年に渡る3世代の物語)\u001b[22m\n\u001b[1m(' A story zan spans 3 generations fō 100 iyāzu.' (100-Nen ni wataru 3 sedai no monogatari))\u001b[22m\n\u001b[1m\u001b[22m\nART: Being the animated gundam series to succeed Gundam 00 on TV, AGE has received some negative lashes for its 'colorful' or 'childish' character art. Nagumo Takuzo (video games Inazuma Eleven and Prof. Layton) is responsible for the character art, and it does give off the impression that it wouldn't respect the serious story of the Asuno Family, nor respect the military fiction genre that commonly follows Gundam The openings are great to watch too. . While I do feel that way, and while I do think their characters faces and noses sometime look lazy, I think the style accentuate the characters. The mecha art is good, and I enjoy checking out blogs for the toy models. There are a few designers who worked on different previous gundam works such as Wing, X, Crossbone, and even 00, but the gundam AGE itself seems to adopt more from 00. You can't help but see Exia within AGE-1. Except the starcraft, there are little to no CGI used anywhere. That's a plus for me! You can follow the battles easily. Background art, like the forests and building structures of the colony, are well done.\n\n\u001b[1mART：ガンダム00をテレビで成功させるためのアニメーションガンダムシリーズであるAGEは、「カラフル」または「幼稚」のキャラクターアートのために、いくつかのネガティブなまつげを受けています。  Naguo Takuzo（ビデオゲームInazuma ElevenとLayton教授）はキャラクターアートを担当しており、Asunoファミリーの深刻な話を尊重しない印象を与えたり、ガンダムに続く一般的な軍事的なジャンル 開口部も見ることができます。 。 私はそのように感じていますが、私は自分のキャラクターが顔を出していると思っていて、鼻はいつか怠け者に見えるのですが、そのスタイルがそのキャラクターを強調してくれると思います。 メカの芸術はいいですし、おもちゃのモデルのブログをチェックするのも楽しいです。  Wing、X、Crossbone、さらには00のような前回のガンダム作品に取り組んでいたデザイナーがいくつかいますが、ガンダムAGE自体は00より多くを採用しているようです。あなたはAGE-1内でExiaを見ることはできません。 スタークラフトを除いて、どこにもCGIはほとんどない。 それは私のプラスです！ あなたは簡単に戦いに従うことができます。 背景技術は、森林や植民地の建物構造のように、よく行われています。\u001b[22m\n\u001b[1m(Āto: Gandamu 00 o terebide seikō sa seru tame no animēshongandamushirīzudearu AGE wa,`karafuru' matawa `yōchi' no kyarakutāāto no tame ni, ikutsu ka no negatibuna matsuge o ukete imasu. Naguo Takuzo (bideogēmu Inazuma Eleven to reiton kyōju) wa kyarakutāāto o tantō shite ori, Asuno famirī no shinkokuna hanashi o sonchō shinai inshō o atae tari, Gandamu ni tsudzuku ippantekina gunji-tekina janru. Watashi wa sonoyōni kanjite imasuga, watashi wa jibun no kyarakutā ga kao o dashite iru to omotte ite, hana wa itsuka namakemono ni mieru nodesuga, sono sutairu ga sono kyarakutā o kyōchō shite kureru to omoimasu. Meka no geijutsu wa īdesushi, omocha no moderu no burogu o chekku suru no mo tanoshīdesu. Uingu, X, Crossbone, sarani wa 00 no yōna zenkai no Gandamu sakuhin ni torikunde ita dezainā ga ikutsu ka imasuga, Gandamu AGE jitai wa 00 yori ōku o saiyō shite iru yōdesu. Anata wa AGE - 1-nai de Exia o miru koto wa dekimasen. Sutākurafuto o nozoite, dokoni mo CGI wa hotondo nai. Sore wa watashi no purasudesu! Anata wa kantan ni tatakai ni shitagau koto ga dekimasu. Haikei gijutsu wa, shinrin ya shokuminchi no tatemono kōzō no yō ni, yoku okonawa rete imasu. Kaikō-bu mo miru koto ga dekimasu.)\u001b[22m\n\u001b[1m\u001b[22m\nSTORY: AGE is developed for younger watchers to recognize the Gundam product, and to appeal to a wide audience, which I think makes it easy to follow. I thought a storyline about three generations of pilots from the same family was a great idea. This leaves things to have small develop time. Destruction and violence takes place; also, it has features that are orthodox to the previous shows like the Earth Federation and space colonies, a youthful gundam pilot compelled to battle with a super weapon designed by his family, and military personnel and civilians escaping on a spacecraft. Explaining more may be giving out spoilers, but you if you're familiar with the UC series, you can probably point them out while watching AGE. Plus, I think the UE are a cool enemy. Their vicious fighting tactics, and the Federation's helplessness against them, make them interesting to watch. On the other hand however, the story being VERY linear and being unfair to its supporting characters is a negative. Since the storyline is split into three generations, time passes quickly and the seasons are shortened. Plenty of climaxes, but short seasons.\n\n\u001b[1mストーリー：AGEは、若手ウォッチャーがガンダムの製品を認識し、幅広い聴衆にアピールするために開発されました。 私は同じ家族のパイロットの約3世代のストーリーラインが素晴らしいアイデアだと思った。 これは、小さな開発時間を持つものを残す。 破壊と暴力が起こる。 また、地球連合や宇宙植民地、家族によって設計された超兵器と戦うために強制された若いガンダムパイロット、そして宇宙船から逃れる軍人や民間人など、これまでのショーとは正反対の特徴を持っています。 より多くのことを説明することは、スポイラーを与えるかもしれませんが、あなたがUCシリーズをよく知っていれば、AGEを見ながらそれらを指摘することができます。 さらに、私はUEがクールな敵だと思う。 彼らの悪質な戦術と連邦政府の無力さは、彼らを見て興味深いものにします。 しかし一方で、ストーリーは非常に線形であり、その支持キャラクターにとって不公平であるという話は否定的です。 ストーリーラインは3世代に分割されているので、時間がすばやく進み、季節が短くなります。 クライマックスはたくさんありますが、シーズンは短いです。\u001b[22m\n\u001b[1m(Sutōrī: AGE wa, wakate u~otchā ga Gandamu no seihin o ninshiki shi, habahiroi chōshū ni apīru suru tame ni kaihatsu sa remashita. Watashi wa onaji kazoku no pairotto no yaku 3 sedai no sutōrīrain ga subarashī aideada to omotta. Hakai to bōryoku ga okoru. Mata, chikyū rengō ya uchū shokuminchi, kazoku ni yotte sekkei sa reta chō heiki to tatakau tame ni kyōsei sa reta wakai gandamupairotto, soshite uchūsen kara nogareru gunjin ya minkan hito nado, kore made no shō to wa seihantai no tokuchō o motte imasu. Yori ōku no koto o setsumei suru koto wa, supoirā o ataeru kamo shiremasenga, anata ga UC shirīzu o yoku shitte ireba, AGE o minagara sorera o shiteki suru koto ga dekimasu. Sarani, watashi wa UE ga kūruna tekida to omou. Karera no akushitsuna senjutsu to renbōseifu no muryoku-sa wa, karera o mite kyōmibukai mono ni shimasu. Shikashi ippō de, sutōrī wa hijō ni senkeideari, sono shiji kyarakutā ni totte fukōheidearu to iu hanashi wa hitei-tekidesu. Sutōrīrain wa 3 sedai ni bunkatsu sa rete irunode, jikan ga subayaku susumi, kisetsu ga mijikaku narimasu. Kuraimakkusu wa takusan arimasuga, shīzun wa mijikaidesu. Kore wa, chīsana kaihatsu jikan o motsu mono o nokosu.)\u001b[22m\n\u001b[1m\u001b[22m\nSOUND: Lovely music. The OPs and EDs are a mix of rock and pop. I especially like the opening themes 'Asu he' and 'SHARP'. The ED 'My World' is well done too. Voice-wise, Kazuhiko Inoue (Jerid from Z gundam, Gai from ASTRAY) does well as a narrator. Like a grandfather to his grandchildren, his gruff tone relays the setting's tense reality, of generations thrown into chaos by the UE. Along with him, other VA from previous gundam works such as Sakaguchi Daisuke (Usso from Victory Gundam), Yusa Koji (a minor in gundam X), Ono Daisuke (Sven Cal of STARGAZER), Toichi Hiroki (Lasse of 00), Endoh Aya , (Kimie Crossroad in 00), Romi Paku (Loran from Turn A), Suwabe Junichi (Sting of SEED DESTINY), and Kusanoki Taiten appear in the cast. The main characters (Eguchi Takuya, Toyonaga Toshiyuki, Yamamoto Kazutomi) are voiced by more-or-less new VAs but they do well in portraying the boys.\n\n\u001b[1mサウンド：素敵な音楽。  OPとEDはロックとポップのミックスです。 私は特にオープニングテーマ「Asu he」と「SHARP」が好きです。  ED「My World」もうまくいっています。 ボイスワイズ、井上和彦（Zガンダム出身のジェリッド、アストレイ出身のガイ）は語り手としてはうまくいきます。 彼の孫に祖父のように、彼のぞっとする音色は、UEによって混沌に投げ込まれた世代の緊張した現実の現実を伝えます。 それと並行して、坂口大輔（勝利ガンダムからのUsso）、宇宙飛行士（Xガンダムの小人）、小野大輔（STARGAZERのSve​​nCal）、宇宙飛行士（Lace of 00）、遠藤綾 、キミ・クロスロード（00）、ロミ・パク（ロラン・Aターン）、諏訪部純一（SEED DESTINY）、草なぎ大仁が登場する。 主人公（江口拓也、豊永俊之、山本一夫）は、若干の新生児派遣によって声が上がりますが、男の子を描くのにはうまくいきます。\u001b[22m\n\u001b[1m(Saundo: Sutekina ongaku. OP to ED wa rokku to poppu no mikkusudesu. Watashi wa tokuni ōpuningutēma `Asu he' to `shāpu' ga sukidesu. ED `My World' mo umaku itte imasu. Boisuwaizu, inoue kazuhiko (zettogandamu shusshin no jeriddo, asutorei shusshin no gai) wa katarite to shite wa umaku ikimasu. Kare no mago ni sofu no yō ni, kare no zotto suru neiro wa, UE ni yotte konton ni nagekoma reta sedai no kinchō shita genjitsu no genjitsu o tsutaemasu. Soreto heikōshite, Sakaguchi Daisuke (shōri Gandamu kara no Usso), uchū hikō-shi (X Gandamu no kobito), ono daisuke (sutāgeizā no Sve ​​ nCal), uchū hikō-shi (rēsu of 00), endō aya, Kimi kurosurōdo (00), Romi paku (roran A tān), Suwabe Jun'ichi (shīdo desucha), Kusanagi Ōhito ga tōjō suru. Shujinkō (eguchi takuya, Toyonaga Toshiyuki, yamamoto kazuo) wa, jakkan no shinseiji haken ni yotte koe ga agarimasuga, otokonoko o kaku no ni wa umaku ikimasu.)\u001b[22m\n\nTranslations of \u001b[4mSOUND: Lovely music. The OPs and EDs are a mix of rock and pop. I especially like the opening themes 'Asu he' and 'SHARP'. The ED 'My World' is well done too. Voice-wise, Kazuhiko Inoue (Jerid from Z gundam, Gai from ASTRAY) does well as a narrator. Like a grandfather to his grandchildren, his gruff tone relays the setting's tense reality, of generations thrown into chaos by the UE. Along with him, other VA from previous gundam works such as Sakaguchi Daisuke (Usso from Victory Gundam), Yusa Koji (a minor in gundam X), Ono Daisuke (Sven Cal of STARGAZER), Toichi Hiroki (Lasse of 00), Endoh Aya , (Kimie Crossroad in 00), Romi Paku (Loran from Turn A), Suwabe Junichi (Sting of SEED DESTINY), and Kusanoki Taiten appear in the cast. The main characters (Eguchi Takuya, Toyonaga Toshiyuki, Yamamoto Kazutomi) are voiced by more-or-less new VAs but they do well in portraying the boys.\u001b[24m\n[ \u001b[4mEnglish\u001b[24m -> \u001b[1m日本語\u001b[22m ]\n\n\u001b[4mSOUND: Lovely music.\u001b[24m\n    \u001b[1mサウンド：素敵な音楽。\u001b[22m, \u001b[1mSOUND：素敵な音楽。\u001b[22m\n\u001b[4mThe OPs and EDs are a mix of rock and pop.\u001b[24m\n    \u001b[1mOPとEDはロックとポップのミックスです。\u001b[22m, \u001b[1mOPとEDSはロックやポップスのミックスです。\u001b[22m\n\u001b[4mI especially like the opening themes 'Asu he' and 'SHARP'.\u001b[24m\n    \u001b[1m私は特にオープニングテーマ「Asu he」と「SHARP」が好きです。\u001b[22m, \u001b[1m私は特に開くテーマ「明日彼 'と' 'シャープ'のような。\u001b[22m\n\u001b[4mThe ED 'My World' is well done too.\u001b[24m\n    \u001b[1mED「My World」もうまくいっています。\u001b[22m, \u001b[1mED「私の世界」はよく、あまりにも行われます。\u001b[22m\n\u001b[4mVoice-wise, Kazuhiko Inoue (Jerid from Z gundam, Gai from ASTRAY) does well as a narrator.\u001b[24m\n    \u001b[1mボイスワイズ、井上和彦（Zガンダム出身のジェリッド、アストレイ出身のガイ）は語り手としてはうまくいきます。\u001b[22m, \u001b[1m音声面では、井上和彦（Zガンダム、街からASTRAYからJerid）がナレーターとしても行います。\u001b[22m\n\u001b[4mLike a grandfather to his grandchildren, his gruff tone relays the setting's tense reality, of generations thrown into chaos by the UE.\u001b[24m\n    \u001b[1m彼の孫に祖父のように、彼のぞっとする音色は、UEによって混沌に投げ込まれた世代の緊張した現実の現実を伝えます。\u001b[22m, \u001b[1m彼の孫の祖父と同じように、彼のぶっきらぼうな口調は、UEによって混乱に投げ込ま世代の、設定の緊張現実を中継します。\u001b[22m\n\u001b[4mAlong with him, other VA from previous gundam works such as Sakaguchi Daisuke (Usso from Victory Gundam), Yusa Koji (a minor in gundam X), Ono Daisuke (Sven Cal of STARGAZER), Toichi Hiroki (Lasse of 00), Endoh Aya\u001b[24m\n    \u001b[1mそれと並行して、坂口大輔（勝利ガンダムからのUsso）、宇宙飛行士（Xガンダムの小人）、小野大輔（STARGAZERのSvenCal）、宇宙飛行士（Lace of 00）、遠藤綾\u001b[22m, \u001b[1m彼と一緒に、他のVAなど阪口大助（ヴィクトリーガンダムからUsso）、遊佐浩二（ガンダムXのマイナー）、小野大輔（STARGAZERのスヴェンカル）、東一弘樹（00のラッセ）、遠藤綾など、以前のガンダム作品から\u001b[22m\n\u001b[4m, (Kimie Crossroad in 00), Romi Paku (Loran from Turn A), Suwabe Junichi (Sting of SEED DESTINY), and Kusanoki Taiten appear in the cast.\u001b[24m\n    \u001b[1m、キミ・クロスロード（00）、ロミ・パク（ロラン・Aターン）、諏訪部純一（SEED DESTINY）、草なぎ大仁が登場する。\u001b[22m, \u001b[1m、（00におけるKimieクロスロード）、ロミパク（ターンAからロラン）、諏訪部順一（SEED DESTINYののスティング）、およびKusanoki Taitenはキャストに表示されます。\u001b[22m\n\u001b[4mThe main characters (Eguchi Takuya, Toyonaga Toshiyuki, Yamamoto Kazutomi) are voiced by more-or-less new VAs but they do well in portraying the boys.\u001b[24m\n    \u001b[1m主人公（江口拓也、豊永俊之、山本一夫）は、若干の新生児派遣によって声が上がりますが、男の子を描くのにはうまくいきます。\u001b[22m, \u001b[1mメインキャラクター（江口拓也、豊永利行、山本Kazutomi）は、多かれ少なかれ、新規のVAによって表明されているが、彼らは男の子を描いでよくやります。\u001b[22m\n\u001b[1m\u001b[22m\nCHARACTER: Like I said, the story is straight-forward. The main characters, as members of the Asuno family, receive the most development. Each season quickly passes by, leaving characters and replacing them before you get to know them well enough. This feels pretty bad when it comes to romantic relationships. One thing that bothers me is that because the gundam is a force to be reckon with, many (not all) side characters are more-or-less insignificant. Also, the antagonists are so vicious in their supposedly 'fair goal' that they seem like monsters more than anything.\n\n\u001b[1mキャラクター：私が言ったように、ストーリーはまっすぐです。 主人公は、浅野家の一員として、最も発展しています。 各シーズンはすぐに通り抜け、文字を残して置き換えてから、それらを十分に知るようにします。 これはロマンチックな関係になるとかなり気分が悪くなります。 私を悩ますことの1つは、ガンダムが考慮する力であるため、多くの（すべてではない）サイドキャラクターが多かれ少なかれ重要ではないということです。 また、アンタゴニストは、おそらくは「公平なゴール」で非常に悪質で、何よりも怪物のように見える。\u001b[22m\n\u001b[1m(Kyarakutā: Watashi ga itta yō ni, sutōrī wa massugudesu. Shujinkō wa, Asano-ka no ichiin to shite, mottomo hatten shite imasu. Kaku shīzun wa sugu ni tōrinuke, moji o nokoshite okikaete kara, sorera o jūbun ni shiru yō ni shimasu. Kore wa romanchikkuna kankei ni naruto kanari kibun ga waruku narimasu. Watashi o nayamasu koto no 1tsu wa, Gandamu ga kōryo suru chikaradearu tame, ōku no (subetede wa nai) saidokyarakutā ga ōkare sukunakare jūyōde wa nai to iu kotodesu. Mata, antagonisuto wa, osorakuha `kōheina gōru' de hijō ni akushitsude, naniyori mo kaibutsu no yō ni mieru.)\u001b[22m\n\nTranslations of \u001b[4mCHARACTER: Like I said, the story is straight-forward. The main characters, as members of the Asuno family, receive the most development. Each season quickly passes by, leaving characters and replacing them before you get to know them well enough. This feels pretty bad when it comes to romantic relationships. One thing that bothers me is that because the gundam is a force to be reckon with, many (not all) side characters are more-or-less insignificant. Also, the antagonists are so vicious in their supposedly 'fair goal' that they seem like monsters more than anything.\u001b[24m\n[ \u001b[4mEnglish\u001b[24m -> \u001b[1m日本語\u001b[22m ]\n\n\u001b[4mCHARACTER: Like I said, the story is straight-forward.\u001b[24m\n    \u001b[1mキャラクター：私が言ったように、ストーリーはまっすぐです。\u001b[22m, \u001b[1mCHARACTER：私が言ったように、物語は単純明快です。\u001b[22m\n\u001b[4mThe main characters, as members of the Asuno family, receive the most development.\u001b[24m\n    \u001b[1m主人公は、浅野家の一員として、最も発展しています。\u001b[22m, \u001b[1mメインキャラクターは、Asunoファミリーのメンバーとして、ほとんどの開発を受け取ります。\u001b[22m\n\u001b[4mEach season quickly passes by, leaving characters and replacing them before you get to know them well enough.\u001b[24m\n    \u001b[1m各シーズンはすぐに通り抜け、文字を残して置き換えてから、それらを十分に知るようにします。\u001b[22m, \u001b[1m各シーズンはすぐに文字を残して、あなたは十分にそれらを知るようになる前にそれらを置き換える、通り過ぎます。\u001b[22m\n\u001b[4mThis feels pretty bad when it comes to romantic relationships.\u001b[24m\n    \u001b[1mこれはロマンチックな関係になるとかなり気分が悪くなります。\u001b[22m, \u001b[1mそれはロマンチックな関係に来るときこれはかなり悪い感じ。\u001b[22m\n\u001b[4mOne thing that bothers me is that because the gundam is a force to be reckon with, many (not all) side characters are more-or-less insignificant.\u001b[24m\n    \u001b[1m私を悩ますことの1つは、ガンダムが考慮する力であるため、多くの（すべてではない）サイドキャラクターが多かれ少なかれ重要ではないということです。\u001b[22m, \u001b[1m私を悩ますことの一つは、ガンダムを数えるべき力であるので、多くの（すべてではない）側の文字は、多かれ少なかれ重要ではないということです。\u001b[22m\n\u001b[4mAlso, the antagonists are so vicious in their supposedly 'fair goal' that they seem like monsters more than anything.\u001b[24m\n    \u001b[1mまた、アンタゴニストは、おそらくは「公平なゴール」で非常に悪質で、何よりも怪物のように見える。\u001b[22m, \u001b[1mまた、アンタゴニストは、彼らが何よりもモンスターのように見える彼らのたぶん「公正な目標」で非常に悪質です。\u001b[22m\n\u001b[1m\u001b[22m\nENJOY/OVERALL: Simplicity in story, bad direction with some characters. I like the family concept in AGE and the evolution of the gundam. Good music. I think it's a fair show and has the gundam essentials. If this show teaches you anything, don't give in to anger and spite.\n\n\u001b[1mENJOY / OVERALL：物語のシンプルさ、いくつかの文字の悪い方向。 私はAGEの家族概念とガンダムの進化が好きです。 良い音楽。 私はそれが公正なショーだと思うし、ガンダムの本質を持っている。 このショーがあなたに何かを教えてくれたら、怒りや嫌悪感を与えないでください。\u001b[22m\n\u001b[1m(ENJOY/ OVERALL: Monogatari no shinpuru-sa, ikutsu ka no moji no warui hōkō. Watashi wa AGE no kazoku gainen to Gandamu no shinka ga sukidesu. Yoi ongaku. Watashi wa sore ga kōseina shōda to omoushi, Gandamu no honshitsu o motte iru. Kono shō ga anata ni nanika o oshiete kuretara, ikari ya ken'o-kan o ataenaide kudasai.)\u001b[22m\n\nTranslations of \u001b[4mENJOY/OVERALL: Simplicity in story, bad direction with some characters. I like the family concept in AGE and the evolution of the gundam. Good music. I think it's a fair show and has the gundam essentials. If this show teaches you anything, don't give in to anger and spite.\u001b[24m\n[ \u001b[4mEnglish\u001b[24m -> \u001b[1m日本語\u001b[22m ]\n\n\u001b[4mENJOY/OVERALL: Simplicity in story, bad direction with some characters.\u001b[24m\n    \u001b[1mENJOY / OVERALL：物語のシンプルさ、いくつかの文字の悪い方向。\u001b[22m, \u001b[1mOVERALL / ENJOY：物語の中でシンプル、悪い方向に一部の文字で。\u001b[22m\n\u001b[4mI like the family concept in AGE and the evolution of the gundam.\u001b[24m\n    \u001b[1m私はAGEの家族概念とガンダムの進化が好きです。\u001b[22m, \u001b[1m私はAGEとガンダムの進化における家族の概念が好き。\u001b[22m\n\u001b[4mGood music.\u001b[24m\n    \u001b[1m良い音楽。\u001b[22m\n\u001b[4mI think it's a fair show and has the gundam essentials.\u001b[24m\n    \u001b[1m私はそれが公正なショーだと思うし、ガンダムの本質を持っている。\u001b[22m, \u001b[1m私はそれが公正ショーだとガンダムの必需品を持っていると思います。\u001b[22m\n\u001b[4mIf this show teaches you anything, don't give in to anger and spite.\u001b[24m\n    \u001b[1mこのショーがあなたに何かを教えてくれたら、怒りや嫌悪感を与えないでください。\u001b[22m, \u001b[1mこのショーはあなたに何かを教えている場合は、怒りともかかわらずに与えていません。\u001b[22m"
  },
  {
    "title": "Mobile_Suit_Gundam_AGE",
    "id": "10808",
    "url": "https://myanimelist.net/anime/10808/Mobile_Suit_Gundam_AGE",
    "user": "SolXero",
    "profile": "/profile/SolXero/reviews",
    "pages": "2",
    "number": "2",
    "link": "/reviews.php?id=82938",
    "jp": "--- | --- | ---\n全体的な|  6\n--- | ---\nストーリー|  6\nアニメーション|  7\nサウンド|  7\nキャラクター|  5\n|  6\n\nこれは私の最初のガンダムシリーズではありませんが、アニメのための私の最初のレビューです。それは私の最後のものではありません。 うまくいけば、これは役に立つと思う人もいます。\n\n私はメカアニメとガンダムシリーズの両方を熱心に捉えてきました。 私は最初に言葉と最初のレビューの両方から、私のベストを尽くし、このシリーズを完全に避けることをお勧めしませんでした。 結局のところ、私はこの新しいシリーズがどのように競争にどのように積み重なっているかを自分自身で見極めることに決めました。\n\n概要はありません。すぐに行きます。\n\nストーリー：6\n\nストーリーとアイデア自体は悪くありません。 むしろバンダイが思い付いたのは全く新しいアイデアでした。  3世代にわたるガンダムシリーズ。 紙の上で素晴らしいですが、途中で物事がちょうどうんざりになりました。\n\n最初のものから始めることができます：UEまたはVagan。  Flitとcoの前提。 それは本当に不信の中断を広げる。 最高の真ちゅうは、誰が、何がVagansであるかを知っていることが明らかになっているにもかかわらず、このようなシナリオを15以上のエピソードで視聴者に提示するには、あまりにも多すぎるため、 状況の愚かさ。 エイリアンとして認識できるものと戦うことはできません。 与えられた理由の大半は、ガンダムシリーズなのでシナリオがうまくいきません。 これを見ているより良い方法は、シナリオ自体が実行されていないことです。 未知の敵は必ずしもエイリアンに翻訳する必要はないことを認識してください。 高度な技術によって破壊を引き起こし、目撃者や証拠を残すことのない無情な人間の不正なグループも、未知の敵の型に合うように形作ることができます。 何があっても、上に説明したものは、Vaganと同様に適合します。 噂や物語を通して、それが最終的にどのようにキャラクターがエイリアンであると信じるものになるかは分かります。 しかし、地球連合でさえも、ヴァーガンは自分自身がエイリアンであると信じることができますか？\n\n2番目のことは、ペーシングであり、3世代/アークの前提は疑わしいです。 フリットのアークに関しては、重要でない問題に費やされた5〜6回のエピソードを数えることができます。 興味深いものの、Fardainの円弧は、プロットを運転したり、キャラクター開発を進める上で、ほとんど何もしません。  Boyageの死がFlitの開発に影響を与えていることは確かですが、それはいくつかのエピソードがあり、Fardainに3-4のエピソードを浪費することなくセットアップされている可能性があります。 基本的に再び言及されなかったEubaとZalamに費やされた時間は、WoolfやLarganやその他のプロットポイントのようなキャラクターを開発するために使われていた可能性があります。  Asemuのアークが面白かったのですが、アークの奇妙なペーシングは観客に与える影響を軽減します。  Asemuが彼の弧の最後の2つのエピソードの近くで、そしてWoolfが死んだ後でのみ、彼の致命的な欠陥の突然の実現に来ると信じるのは難しいです。 彼の嫉妬の結果（彼の死の経験を含む）の結果としてAsemuに起こる他のすべての光を作るだけでなく、プロットポイントを包み込むための迅速な修正としてWoolfの死を作ることによって視聴者を軽視するかもしれない。  3つのアークのうち、キオのアークはおそらく最も退屈で、物語には何も追加しません。 プロジェクト・エデンの本当の意図とEXA-DBは明らかにされていますが、ストーリーを包み込むのにはほとんど役立ちません。\n\n全体的にストーリーは非常に平凡で、より良いものになる可能性があります。\n\nアート：7\n\nキャラクターとモビルスーツの芸術デザインは、本当にノスタルジックな思い出をもたらします。 彼らは子供のように見えると不平を言う人もいますが、アートデザインはもっとMSGタイプのルーツに戻ったかのように感じます。 それは、モバイルスーツのデザインのいくつかが良いかもしれないと述べた。 これはVaganモバイルスーツの場合に特に当てはまります。 彼らのほとんどは飛んでいるトカゲのように見えます。 まるで芸術部門が怠け者になっていて、地球連合のためにより多くのモバイルスーツを作る気がしなかったようです。 すべての3つの弧のためにGenoacesに来てください。\n\nサウンド：7\n\n楽曲は堅実です。 彼らはUnicornやMS IGLOOのような素晴らしいものではありませんが、彼らは仕事を完了します。\n\nキャラクター：5\n\nメジャーなキャラクターよりも2つのエピソードで殺されたマイナーキャラクターに感情移入するほうが、作品に大きな問題があるよりも簡単です。 一部のキャラクターのキャラクター開発は、大したことはありません。\n\nより深刻な例の2つは、ZeheartとKioです。 アニメのかなりの部分を見ると、視聴者はZeheartを、EzelcantのProject Edenと通常の人間の生活を送ることを希望する人との間で闘う人物と見なします。  ZeheartはProject Edenを実行しているかのように見えますが、AsemuとGundamの障害を取り除くのが難しいことがわかります。 それだけでなく、Zeheartは険しくても気遣う指揮官になっています。 だから彼が計画を達成するためにVaganのリーダーになって部下を殺した後、彼が盲目的にEzelcantに提出すると、彼の性格は失われます。 これは、それが彼の性格を発達させる有効な方法ではないが、それは悪い方法であると言っているわけではない。 それはZeheartを作るすべてを矛盾させ、破棄し、その時点までに彼は立ち上がっている。  Zeheartのようなものでも、Project Edenの背後にある真実を見つけた後で、Ezelcantの計画を変えても意味があります。\n\n\nKioに関しては、彼は本当に始まったキャラクターの開発を本当に得たことはありません。 彼は「誰もが守りたい」「戦いをやめよう」といった欲求不満の段階に達しています。 これは彼がVaganのより人道的な側面にさらされていたと考えれば公正ですが、彼はその段階から成長することはありません。 彼は最後の弧のより良い部分のために戦いを止めようと絶望的に努力しており、彼の試みが無意味であり、彼の仲間の死者を見た後も止まない。  Kioは、いつも平和について噴出しているが、実際には何にもなることはない。\n\n機動戦士勝利のガンダムからKioとUsoを比較してください。 キオのように、ウソは常に戦争の現実に砲撃され、彼に近い人の死を見ました。 彼はKioと同じ結論になる小さな時間枠がありますが、戦いを止める唯一の方法は戦争と強制的に戦争を終わらせることだと見て、Usoの性格が発達します。  Usoは平和を重んじますが、彼はそれを求めて戦う必要があると理解し、自分を動機付けるための呼びかけとしてそれを使用するすべての人に彼の見解を強制するのではなく、 この例は、決して起こらなかったことを除いてKioが開発された可能性のある方向性であった可能性があります。\n\nこれらの2つはより顕著な例に過ぎませんが、他の悩みがあります。 エミリーは、友情的で強迫観念に近い、関係する友人の貧弱なバージョンであったという主張をすることができます。 ユリインは、フラットの恋人で、一次元なので、彼女は愛の関心事として追加されただけで、フリートのヴァーガンの憎しみを扇動するように見えます。\n\nディレクティングとライティングのチームが一貫したキャラクターを作ってプロットポイントを解決しようと苦労しているように見えるので、面白いキャラクターが終わり近くに見えるかもしれません。 彼は復讐と憎しみに追い込まれたキャラクターを見て、彼が今までに行ったあらゆる決定に影響を与えるのは面白かった（少なくともガンダムフランチャイズでは）。 それでも、彼はプロットを結びつけるために最後に柔らかくなります。 これもまた、非常に悪いキャラクター開発の原因となります。\n\nこれらのキャラクタはすべて、アニメがより良く開発された場合に、アニメを少し上手にするために使用されていた可能性があります。\n\n全体的な印象：6\n\n誰もがそれを作るように悪いことでしたか？ ではない正確に。 実際に私を怒らせて、このアニメを一緒に落とすような気分にさせた部分はありましたか？ もちろんです。 ガンダムのファンとして、私はガンダムシードの運命であるファンフィックプロットと同じように、私は失望していませんでした。 しかし、それはあまり意味がありません。 ガンダムフランチャイズとサンライズが大金を稼ぐ機会がありましたが、いたずらな演出と執筆のために多くのことが無駄になりました。\n\n平均的なウォッチャーのために、彼らはこれからいくらか軽い楽しみを得るかもしれません。 それでも、時には、それは時には過度の負担と退屈を感じるかもしれません。 それは普通のガンダムシリーズとして立派で、ガンダムシリーズとして常に記憶されています。",
    "notes": "---|---|---\n\n\u001b[1m--- | --- | ---\u001b[22m\n\u001b[1m(-- - | -- - | -- -)\u001b[22m\n\nTranslations of \u001b[4m---|---|---\u001b[24m\n[ \u001b[4mEnglish\u001b[24m -> \u001b[1m日本語\u001b[22m ]\n\n\u001b[4m---|---|---\u001b[24m\n    \u001b[1m--- | --- | ---\u001b[22m\nOverall | 6\n\n\u001b[1m全体的な|  6\u001b[22m\n\u001b[1m(Zentai-tekina | 6)\u001b[22m\n\nTranslations of \u001b[4mOverall | 6\u001b[24m\n[ \u001b[4mEnglish\u001b[24m -> \u001b[1m日本語\u001b[22m ]\n\n\u001b[4mOverall |\u001b[24m\n    \u001b[1m全体的な|\u001b[22m, \u001b[1m総合的な|\u001b[22m\n\u001b[4m6\u001b[24m\n    \u001b[1m6\u001b[22m\n---|---\n\n\u001b[1m--- | ---\u001b[22m\n\u001b[1m(-- - | -- -)\u001b[22m\n\nTranslations of \u001b[4m---|---\u001b[24m\n[ \u001b[4mEnglish\u001b[24m -> \u001b[1m日本語\u001b[22m ]\n\n\u001b[4m---|---\u001b[24m\n    \u001b[1m--- | ---\u001b[22m\nStory | 6\n\n\u001b[1mストーリー|  6\u001b[22m\n\u001b[1m(Sutōrī | 6)\u001b[22m\n\nTranslations of \u001b[4mStory | 6\u001b[24m\n[ \u001b[4mEnglish\u001b[24m -> \u001b[1m日本語\u001b[22m ]\n\n\u001b[4mStory |\u001b[24m\n    \u001b[1mストーリー|\u001b[22m\n\u001b[4m6\u001b[24m\n    \u001b[1m6\u001b[22m\nAnimation | 7\n\n\u001b[1mアニメーション|  7\u001b[22m\n\u001b[1m(Animēshon | 7)\u001b[22m\n\nTranslations of \u001b[4mAnimation | 7\u001b[24m\n[ \u001b[4mEnglish\u001b[24m -> \u001b[1m日本語\u001b[22m ]\n\n\u001b[4mAnimation |\u001b[24m\n    \u001b[1mアニメーション|\u001b[22m\n\u001b[4m7\u001b[24m\n    \u001b[1m7\u001b[22m\nSound | 7\n\n\u001b[1mサウンド|  7\u001b[22m\n\u001b[1m(Saundo | 7)\u001b[22m\n\nTranslations of \u001b[4mSound | 7\u001b[24m\n[ \u001b[4mEnglish\u001b[24m -> \u001b[1m日本語\u001b[22m ]\n\n\u001b[4mSound |\u001b[24m\n    \u001b[1mサウンド|\u001b[22m\n\u001b[4m7\u001b[24m\n    \u001b[1m7\u001b[22m\nCharacter | 5\n\n\u001b[1mキャラクター|  5\u001b[22m\n\u001b[1m(Kyarakutā | 5)\u001b[22m\n\nTranslations of \u001b[4mCharacter | 5\u001b[24m\n[ \u001b[4mEnglish\u001b[24m -> \u001b[1m日本語\u001b[22m ]\n\n\u001b[4mCharacter |\u001b[24m\n    \u001b[1mキャラクター|\u001b[22m, \u001b[1m文字|\u001b[22m\n\u001b[4m5\u001b[24m\n    \u001b[1m5\u001b[22m\nEnjoyment | 6\n\n\u001b[1m|  6\u001b[22m\n\u001b[1m(| 6)\u001b[22m\n\nTranslations of \u001b[4mEnjoyment | 6\u001b[24m\n[ \u001b[4mEnglish\u001b[24m -> \u001b[1m日本語\u001b[22m ]\n\n\u001b[4mEnjoyment |\u001b[24m\n    \u001b[1m|\u001b[22m, \u001b[1m楽しさ|\u001b[22m\n\u001b[4m6\u001b[24m\n    \u001b[1m6\u001b[22m\n\u001b[1m\u001b[22m\nThis is my first review for an anime, though this is not my first Gundam series and it will not be my last. Hopefully some will find this useful.\n\n\u001b[1mこれは私の最初のガンダムシリーズではありませんが、アニメのための私の最初のレビューです。それは私の最後のものではありません。 うまくいけば、これは役に立つと思う人もいます。\u001b[22m\n\u001b[1m(Kore wa watashi no saisho no gandamushirīzude wa arimasenga, anime no tame no watashi no saisho no rebyūdesu. Sore wa watashi no saigo no monode wa arimasen. Umaku ikeba, koreha yakunitatsu to omou hito mo imasu.)\u001b[22m\n\nTranslations of \u001b[4mThis is my first review for an anime, though this is not my first Gundam series and it will not be my last. Hopefully some will find this useful.\u001b[24m\n[ \u001b[4mEnglish\u001b[24m -> \u001b[1m日本語\u001b[22m ]\n\n\u001b[4mThis is my first review for an anime, though this is not my first Gundam series and it will not be my last.\u001b[24m\n    \u001b[1mこれは私の最初のガンダムシリーズではありませんが、アニメのための私の最初のレビューです。それは私の最後のものではありません。\u001b[22m, \u001b[1mこれが私の最初のガンダムシリーズではありません、それは私の最後ではありませんが、これは、アニメのための私の最初のレビューです。\u001b[22m\n\u001b[4mHopefully some will find this useful.\u001b[24m\n    \u001b[1mうまくいけば、これは役に立つと思う人もいます。\u001b[22m, \u001b[1mうまくいけば、いくつかは、これが役に立つでしょう。\u001b[22m\n\u001b[1m\u001b[22m\nI've been an avid watcher of both mecha animes and the Gundam series itself. I was initially discouraged, from both word of mouth and initial reviews, to do my best and avoid this series entirely. Eventually, I decided to see for myself just how this new series stacks up to the competition.\n\n\u001b[1m私はメカアニメとガンダムシリーズの両方を熱心に捉えてきました。 私は最初に言葉と最初のレビューの両方から、私のベストを尽くし、このシリーズを完全に避けることをお勧めしませんでした。 結局のところ、私はこの新しいシリーズがどのように競争にどのように積み重なっているかを自分自身で見極めることに決めました。\u001b[22m\n\u001b[1m(Watashi wa meka anime to gandamushirīzu no ryōhō o nesshin ni toraete kimashita. Watashi wa saisho ni kotoba to saisho no rebyū no ryōhō kara, watashi no besuto o tsukushi, kono shirīzu o kanzen ni yokeru koto o o susume shimasendeshita. Kekkyokunotokoro, watashi wa kono atarashī shirīzu ga dono yō ni kyōsō ni dono yō ni tsumikasanatte iru ka o jibun jishin de mikiwameru koto ni kimemashita.)\u001b[22m\n\nTranslations of \u001b[4mI've been an avid watcher of both mecha animes and the Gundam series itself. I was initially discouraged, from both word of mouth and initial reviews, to do my best and avoid this series entirely. Eventually, I decided to see for myself just how this new series stacks up to the competition.\u001b[24m\n[ \u001b[4mEnglish\u001b[24m -> \u001b[1m日本語\u001b[22m ]\n\n\u001b[4mI've been an avid watcher of both mecha animes and the Gundam series itself.\u001b[24m\n    \u001b[1m私はメカアニメとガンダムシリーズの両方を熱心に捉えてきました。\u001b[22m, \u001b[1m私は両方のメカアニメやガンダムシリーズ自体の熱心なウォッチャーしてきました。\u001b[22m\n\u001b[4mI was initially discouraged, from both word of mouth and initial reviews, to do my best and avoid this series entirely.\u001b[24m\n    \u001b[1m私は最初に言葉と最初のレビューの両方から、私のベストを尽くし、このシリーズを完全に避けることをお勧めしませんでした。\u001b[22m, \u001b[1m私が最初に私のベストを尽くすし、完全にこのシリーズを回避するために、口の中の言葉と初期レビューの両方から、がっかりしました。\u001b[22m\n\u001b[4mEventually, I decided to see for myself just how this new series stacks up to the competition.\u001b[24m\n    \u001b[1m結局のところ、私はこの新しいシリーズがどのように競争にどのように積み重なっているかを自分自身で見極めることに決めました。\u001b[22m, \u001b[1m結局、私はこの新しいシリーズは、競争までスタックどれだけ自分のために参照することを決めました。\u001b[22m\n\u001b[1m\u001b[22m\nNo synopsis, lets go right in to the nitty-gritty.\n\n\u001b[1m概要はありません。すぐに行きます。\u001b[22m\n\u001b[1m(Gaiyō wa arimasen. Sugu ni ikimasu.)\u001b[22m\n\nTranslations of \u001b[4mNo synopsis, lets go right in to the nitty-gritty.\u001b[24m\n[ \u001b[4mEnglish\u001b[24m -> \u001b[1m日本語\u001b[22m ]\n\n\u001b[4mNo synopsis, lets go right in to the nitty-gritty.\u001b[24m\n    \u001b[1m概要はありません。すぐに行きます。\u001b[22m, \u001b[1mいいえ概要は、核心に右に行くことができますありません。\u001b[22m\n\u001b[1m\u001b[22m\nStory: 6\n\n\u001b[1mストーリー：6\u001b[22m\n\u001b[1m(Sutōrī: 6)\u001b[22m\n\nTranslations of \u001b[4mStory: 6\u001b[24m\n[ \u001b[4mEnglish\u001b[24m -> \u001b[1m日本語\u001b[22m ]\n\n\u001b[4mStory: 6\u001b[24m\n    \u001b[1mストーリー：6\u001b[22m\n\u001b[1m\u001b[22m\nThe story and idea itself isn't bad. Rather it was quite novel idea that Bandai came up with. A Gundam series spanning three generations. Sounds great on paper, but somewhere along the way things just went awry.\n\n\u001b[1mストーリーとアイデア自体は悪くありません。 むしろバンダイが思い付いたのは全く新しいアイデアでした。  3世代にわたるガンダムシリーズ。 紙の上で素晴らしいですが、途中で物事がちょうどうんざりになりました。\u001b[22m\n\u001b[1m(Sutōrī to aidea jitai wa waruku arimasen. Mushiro Bandai ga omoitsuita no wa mattaku atarashī aideadeshita. 3 Sedai ni wataru gandamushirīzu. Kami no ue de subarashīdesuga, tochū de monogoto ga chōdo unzari ni narimashita.)\u001b[22m\n\nTranslations of \u001b[4mThe story and idea itself isn't bad. Rather it was quite novel idea that Bandai came up with. A Gundam series spanning three generations. Sounds great on paper, but somewhere along the way things just went awry.\u001b[24m\n[ \u001b[4mEnglish\u001b[24m -> \u001b[1m日本語\u001b[22m ]\n\n\u001b[4mThe story and idea itself isn't bad.\u001b[24m\n    \u001b[1mストーリーとアイデア自体は悪くありません。\u001b[22m, \u001b[1mストーリーとアイディア自体は悪いことではありません。\u001b[22m\n\u001b[4mRather it was quite novel idea that Bandai came up with.\u001b[24m\n    \u001b[1mむしろバンダイが思い付いたのは全く新しいアイデアでした。\u001b[22m, \u001b[1mむしろバンダイが思いついたことを非常に斬新なアイデアでした。\u001b[22m\n\u001b[4mA Gundam series spanning three generations.\u001b[24m\n    \u001b[1m3世代にわたるガンダムシリーズ。\u001b[22m, \u001b[1m3世代に渡るガンダムシリーズ。\u001b[22m\n\u001b[4mSounds great on paper, but somewhere along the way things just went awry.\u001b[24m\n    \u001b[1m紙の上で素晴らしいですが、途中で物事がちょうどうんざりになりました。\u001b[22m, \u001b[1m紙の上に素晴らしいサウンドが、どこかの道に沿って物事がちょうどゆがんで行きました。\u001b[22m\n\u001b[1m\u001b[22m\nLets start with the first thing: UE or the Vagan. The premise of Flit and co. That really stretches suspension of disbelief. Even though it is revealed that the top brass knows who and what the Vagans are and with all the foreshadowing, to present such this scenario to the viewers for a little over 15 episodes is a bit too much and can fails to hook on to viewers given the silliness of the situation. fighting against what can be perceived as aliens doesn't work. The majority of the reasons given are somewhere alone the lines of 'the scenario doesn't work because it's a Gundam series'. A better way of looking at this is that the scenario itself is poorly executed. Recognize that unknown enemy doesn't necessarily have to translate to aliens. A rogue group of emotionless humans who cause destruction through advanced technology and never leave behind witnesses or evidence can also be shaped to fit the mold of an unknown enemy. If anything, what is just described above fits similarly to what the Vagan are. Through rumors and stories it is understandable how that will eventually become what the characters believe are aliens. But to have even the Earth Federation believe that the Vagan are aliens themselves?\n\n\u001b[1m最初のものから始めることができます：UEまたはVagan。  Flitとcoの前提。 それは本当に不信の中断を広げる。 最高の真ちゅうは、誰が、何がVagansであるかを知っていることが明らかになっているにもかかわらず、このようなシナリオを15以上のエピソードで視聴者に提示するには、あまりにも多く、視聴者 状況の愚かさ。 エイリアンとして認識できるものと戦うことはできません。 与えられた理由の大半は、ガンダムシリーズなのでシナリオがうまくいきません。 これを見ているより良い方法は、シナリオ自体が実行されていないことです。 未知の敵は必ずしもエイリアンに翻訳する必要はないことを認識してください。 高度な技術によって破壊を引き起こし、目撃者や証拠を残すことのない無情な人間の不正なグループも、未知の敵の型に合うように形作ることができます。 何があっても、上に説明したものは、Vaganと同様に適合します。 噂や物語を通して、それが最終的にどのようにキャラクターがエイリアンであると信じるものになるかは分かります。 しかし、地球連合でさえも、ヴァーガンは自分自身がエイリアンであると信じることができますか？\u001b[22m\n\u001b[1m(Saisho no mono kara hajimeru koto ga dekimasu: UE matawa Vagan. Flit to co no zentei. Eirian to shite ninshiki dekiru mono to tatakau koto wa dekimasen. Atae rareta riyū no taihan wa, gandamushirīzunanode shinario ga umaku ikimasen. Kore o mite iru yoriyoi hōhō wa, shinario jitai ga jikkō sa rete inai kotodesu. Michi no teki wa kanarazushimo eirian ni hon'yaku suru hitsuyō wanai koto o ninshiki shite kudasai. Kōdona gijutsu ni yotte hakai o hikiokoshi, mokugeki-sha ya shōko o nokosu koto no nai mujōna ningen no fuseina gurūpu mo, michi no teki no kata ni au yō ni katachidzukuru koto ga dekimasu. Nani ga atte mo,-jō ni setsumei shita mono wa, Vagan to dōyō ni tekigō shimasu. Uwasa ya monogatari o tōshite, sore ga saishūtekini dono yō ni kyarakutā ga eiriandearu to shinjiru mono ni naru ka wa wakarimasu. Shikashi, chikyū rengōde sae mo, vu~āgan wa jibun jishin ga eiriandearu to shinjiru koto ga dekimasu ka? Sore wa hontōni fushin no chūdan o hirogeru. Saikō no shinchū wa, dare ga, nani ga Vagansdearu ka o shitte iru koto ga akiraka ni natte iru nimokakawarazu, kono yōna shinario o 15 ijō no episōdo de shichō-sha ni teiji suru ni wa, amarini mo ōku, shichō-sha jōkyō no oroka-sa.)\u001b[22m\n\u001b[1m\u001b[22m\nThe second thing is the pacing and premises of the three generations/arcs are suspect. In regards to Flit's arc, I can count 5-6 episodes where it was spent on non-important issues. The Fardain arc, though interesting, does little to nothing in terms of driving the plot or setting up character development. Sure the death of Boyage has an impact on the development of Flit but that happens several episodes down the road and could have been setup without wasting 3-4 episodes on Fardain. Time spent on Euba and Zalam, that were basically never mentioned again, could have been used to develop characters like Woolf or Largan or setup other plot points. Though Asemu's arc was interesting the weird pacing of the arc lessen the impact it could've had on the audience. It is hard to believe that Asemu comes to a sudden realization of his fatal flaw near the last 2 episodes of his arc and only after Woolf dies. Not only does it make light of everything else that happens to Asemu as a result of his jealousy (including his near death experience), it may slight viewers by making Woolf's death as a quick fix to wrap up a plot point. Out of all three arcs, Kio's arc is perhaps the most boring and does nothing to add to the story. Project Eden's true intentions and EXA-DB are revealed, but they add little to help wrap up the story.\n\n\u001b[1m2番目のことは、ペーシングであり、3世代/アークの前提は疑わしいです。 フリットのアークに関しては、重要でない問題に費やされた5〜6回のエピソードを数えることができます。 興味深いものの、Fardainの円弧は、プロットを運転したり、キャラクター開発を進める上で、ほとんど何もしません。  Boyageの死がFlitの開発に影響を与えていることは確かですが、それはいくつかのエピソードがあり、Fardainに3-4のエピソードを浪費することなくセットアップされている可能性があります。 基本的に再び言及されなかったEubaとZalamに費やされた時間は、WoolfやLarganやその他のプロットポイントのようなキャラクターを開発するために使われていた可能性があります。  Asemuのアークが面白かったのですが、アークの奇妙なペーシングは観客に与える影響を軽減します。  Asemuが彼の弧の最後の2つのエピソードの近くで、そしてWoolfが死んだ後でのみ、彼の致命的な欠陥の突然の実現に来ると信じるのは難しいです。 彼の嫉妬の結果（彼の死の経験を含む）の結果としてAsemuに起こる他のすべての光を作るだけでなく、プロットポイントを包み込むための迅速な修正としてWoolfの死を作ることによって視聴者を軽視するかもしれない。  3つのアークのうち、キオのアークはおそらく最も退屈で、物語には何も追加しません。 プロジェクト・エデンの本当の意図とEXA-DBは明らかにされていますが、ストーリーを包み込むのにはほとんど役立ちません。\u001b[22m\n\u001b[1m(2-Banme no koto wa, pēshingudeari, 3 sedai/ āku no zentei wa utagawashīdesu. Furitto no āku ni kanshite wa, jūyōdenai mondai ni tsuiyasa reta 5 〜 6-kai no episōdo o kazoeru koto ga dekimasu. Kyōmibukai mono no, Fardain no enko wa, purotto o unten shi tari, kyarakutā kaihatsu o susumeru ue de, hotondo nani mo shimasen. Boyage no shi ga Flit no kaihatsu ni eikyō o ataete iru koto wa tashikadesuga, sore wa ikutsu ka no episōdo ga ari, Fardain ni 3 - 4 no episōdo o rōhi suru koto naku settoappu sa rete iru kanōsei ga arimasu. Kihontekini futatabi genkyū sa renakatta Euba to Zalam ni tsuiyasa reta jikan wa, Woolf ya Largan ya sonohoka no purotto pointo no yōna kyarakutā o kaihatsu suru tame ni tsukawa rete ita kanōsei ga arimasu. Asemu no āku ga omoshirokatta nodesuga, āku no kimyōna pēshingu wa kankyaku ni ataeru eikyō o keigen shimasu. Asemu ga kare no ko no saigo no 2tsu no episōdo no chikaku de, soshite Woolf ga shinda nochi de nomi, kare no chimei-tekina kekkan no totsuzen no jitsugen ni kuru to shinjiru no wa muzukashīdesu. Kare no shitto no kekka (kare no shi no keiken o fukumu) no kekka to shite Asemu ni okoru ta no subete no hikari o tsukuru dakedenaku, purotto pointo o tsutsumikomu tame no jinsokuna shūsei to shite Woolf no shi o tsukuru koto ni yotte shichō-sha o keishi suru kamo shirenai. 3Ttsu no āku no uchi, Kio no āku wa osoraku mottomo taikutsu de, monogatari ni wa nani mo tsuika shimasen. Purojekuto eden no hontō no ito to ekusa - DB wa akiraka ni sa rete imasuga, sutōrī o tsutsumikomu no ni wa hotondo yakudachimasen.)\u001b[22m\n\u001b[1m\u001b[22m\nOverall the story is extremely mediocre and could have been made to be a lot better.\n\n\u001b[1m全体的にストーリーは非常に平凡で、より良いものになる可能性があります。\u001b[22m\n\u001b[1m(Zentai-teki ni sutōrī wa hijō ni heibon de, yori yoi mono ni naru kanōsei ga arimasu.)\u001b[22m\n\nTranslations of \u001b[4mOverall the story is extremely mediocre and could have been made to be a lot better.\u001b[24m\n[ \u001b[4mEnglish\u001b[24m -> \u001b[1m日本語\u001b[22m ]\n\n\u001b[4mOverall the story is extremely mediocre and could have been made to be a lot better.\u001b[24m\n    \u001b[1m全体的にストーリーは非常に平凡で、より良いものになる可能性があります。\u001b[22m, \u001b[1m全体的な話は非常に平凡で、多くの優れていることが行われている可能性があります。\u001b[22m\n\u001b[1m\u001b[22m\nArt: 7\n\n\u001b[1mアート：7\u001b[22m\n\u001b[1m(Āto: 7)\u001b[22m\n\nTranslations of \u001b[4mArt: 7\u001b[24m\n[ \u001b[4mEnglish\u001b[24m -> \u001b[1m日本語\u001b[22m ]\n\n\u001b[4mArt: 7\u001b[24m\n    \u001b[1mアート：7\u001b[22m\n\u001b[1m\u001b[22m\nThe art designs of the characters and mobile suits really brings back nostalgic memories. Though some complain that they look childish, the art designs feel as though it has gone back to the roots for a more MSG type look. With that said, some of the mobile suit designs could be better. This is especially true of the Vagan mobile suits. Most of them looking like flying lizards. It also seems as though the art department got lazy and didn't feel like making more mobile suits for the Earth Federation. Come on, Genoaces for all three arcs?\n\n\u001b[1mキャラクターとモビルスーツの芸術デザインは、本当にノスタルジックな思い出をもたらします。 彼らは子供のように見えると不平を言う人もいますが、アートデザインはもっとMSGタイプのルーツに戻ったかのように感じます。 それは、モバイルスーツのデザインのいくつかが良いかもしれないと述べた。 これはVaganモバイルスーツの場合に特に当てはまります。 彼らのほとんどは飛んでいるトカゲのように見えます。 まるで芸術部門が怠け者になっていて、地球連合のためにより多くのモバイルスーツを作る気がしなかったようです。 すべての3つの弧のためにGenoacesに来てください。\u001b[22m\n\u001b[1m(Kyarakutā to mobirusūtsu no geijutsu dezain wa, hontōni nosutarujikkuna omoide o motarashimasu. Karera wa kodomo no yōnimieru to fuheiwoiu hito mo imasuga, ātodezain wa motto MSG taipu no rūtsu ni modotta ka no yō ni kanjimasu. Sore wa, mobairusūtsu no dezain no ikutsu ka ga yoi kamo shirenai to nobeta. Kore wa Vagan mobairusūtsu no baai ni tokuni atehamarimasu. Karera no hotondo wa tonde iru tokage no yō ni miemasu. Marude geijutsu bumon ga namakemono ni natte ite, chikyū rengō no tame ni yori ōku no mobairusūtsu o tsukuru ki ga shinakatta yōdesu. Subete no 3ttsu no ko no tame ni Genoaces ni kite kudasai.)\u001b[22m\n\nTranslations of \u001b[4mThe art designs of the characters and mobile suits really brings back nostalgic memories. Though some complain that they look childish, the art designs feel as though it has gone back to the roots for a more MSG type look. With that said, some of the mobile suit designs could be better. This is especially true of the Vagan mobile suits. Most of them looking like flying lizards. It also seems as though the art department got lazy and didn't feel like making more mobile suits for the Earth Federation. Come on, Genoaces for all three arcs?\u001b[24m\n[ \u001b[4mEnglish\u001b[24m -> \u001b[1m日本語\u001b[22m ]\n\n\u001b[4mThe art designs of the characters and mobile suits really brings back nostalgic memories.\u001b[24m\n    \u001b[1mキャラクターとモビルスーツの芸術デザインは、本当にノスタルジックな思い出をもたらします。\u001b[22m, \u001b[1mキャラクターやモビルスーツの技術の設計は、本当に懐かしい思い出を思い出させます。\u001b[22m\n\u001b[4mThough some complain that they look childish, the art designs feel as though it has gone back to the roots for a more MSG type look.\u001b[24m\n    \u001b[1m彼らは子供のように見えると不平を言う人もいますが、アートデザインはもっとMSGタイプのルーツに戻ったかのように感じます。\u001b[22m, \u001b[1mいくつかは、彼らが幼稚に見えると文句を言うけれども、それはより多くのMSG型の一見のためのルーツに戻ってしまったかのように、技術の設計を感じます。\u001b[22m\n\u001b[4mWith that said, some of the mobile suit designs could be better.\u001b[24m\n    \u001b[1mそれは、モバイルスーツのデザインのいくつかが良いかもしれないと述べた。\u001b[22m, \u001b[1mことで、モビルスーツのデザインのいくつかは良いかもしれません。\u001b[22m\n\u001b[4mThis is especially true of the Vagan mobile suits.\u001b[24m\n    \u001b[1mこれはVaganモバイルスーツの場合に特に当てはまります。\u001b[22m, \u001b[1mこれはVaganモビルスーツの特にそうです。\u001b[22m\n\u001b[4mMost of them looking like flying lizards.\u001b[24m\n    \u001b[1m彼らのほとんどは飛んでいるトカゲのように見えます。\u001b[22m, \u001b[1mそれらのほとんどが飛んでトカゲのように見えます。\u001b[22m\n\u001b[4mIt also seems as though the art department got lazy and didn't feel like making more mobile suits for the Earth Federation.\u001b[24m\n    \u001b[1mまるで芸術部門が怠け者になっていて、地球連合のためにより多くのモバイルスーツを作る気がしなかったようです。\u001b[22m, \u001b[1mまた、美術部門は怠け者だかのように思えるし、地球連邦のためのより多くのモビルスーツを作るような気がしませんでした。\u001b[22m\n\u001b[4mCome on, Genoaces for all three arcs?\u001b[24m\n    \u001b[1mすべての3つの弧のためにGenoacesに来てください。\u001b[22m, \u001b[1mすべての3つのアークのため、Genoacesさあ？\u001b[22m\n\u001b[1m\u001b[22m\nSound: 7\n\n\u001b[1mサウンド：7\u001b[22m\n\u001b[1m(Saundo: 7)\u001b[22m\n\nTranslations of \u001b[4mSound: 7\u001b[24m\n[ \u001b[4mEnglish\u001b[24m -> \u001b[1m日本語\u001b[22m ]\n\n\u001b[4mSound: 7\u001b[24m\n    \u001b[1mサウンド：7\u001b[22m\n\u001b[1m\u001b[22m\nThe musical compositions are solid. They are not anything amazing like the Unicorn or MS IGLOO but they get the job done.\n\n\u001b[1m楽曲は堅実です。 彼らはUnicornやMS IGLOOのような素晴らしいものではありませんが、彼らは仕事を完了します。\u001b[22m\n\u001b[1m(Gakkyoku wa kenjitsudesu. Karera wa Unicorn ya MS igurū no yōna subarashī monode wa arimasenga, karera wa shigoto o kanryō shimasu.)\u001b[22m\n\nTranslations of \u001b[4mThe musical compositions are solid. They are not anything amazing like the Unicorn or MS IGLOO but they get the job done.\u001b[24m\n[ \u001b[4mEnglish\u001b[24m -> \u001b[1m日本語\u001b[22m ]\n\n\u001b[4mThe musical compositions are solid.\u001b[24m\n    \u001b[1m楽曲は堅実です。\u001b[22m, \u001b[1m楽曲は固体です。\u001b[22m\n\u001b[4mThey are not anything amazing like the Unicorn or MS IGLOO but they get the job done.\u001b[24m\n    \u001b[1m彼らはUnicornやMS IGLOOのような素晴らしいものではありませんが、彼らは仕事を完了します。\u001b[22m, \u001b[1m彼らは、ユニコーンやMS IGLOOのような驚くべきものではありませんが、彼らは仕事を成し遂げます。\u001b[22m\n\u001b[1m\u001b[22m\nCharacters: 5\n\n\u001b[1mキャラクター：5\u001b[22m\n\u001b[1m(Kyarakutā: 5)\u001b[22m\n\nTranslations of \u001b[4mCharacters: 5\u001b[24m\n[ \u001b[4mEnglish\u001b[24m -> \u001b[1m日本語\u001b[22m ]\n\n\u001b[4mCharacters: 5\u001b[24m\n    \u001b[1mキャラクター：5\u001b[22m\n\u001b[1m\u001b[22m\nWhen it is easier to empathize with a minor character that gets kill off in two episodes than it for a major character than there is a major problem in the works. The character development for some of the characters are just outright bad.\n\n\u001b[1mメジャーなキャラクターよりも2つのエピソードで殺されたマイナーキャラクターで共感するほうが、作品に大きな問題があるよりも簡単です。 一部のキャラクターのキャラクター開発は、大したことはありません。\u001b[22m\n\u001b[1m(Mejāna kyarakutā yori mo 2tsu no episōdo de korosareta mainākyarakutā de kyōkan suru hō ga, sakuhin ni ōkina mondai ga aru yori mo kantandesu. Ichibu no kyarakutā no kyarakutā kaihatsu wa, taishita koto wa arimasen.)\u001b[22m\n\nTranslations of \u001b[4mWhen it is easier to empathize with a minor character that gets kill off in two episodes than it for a major character than there is a major problem in the works. The character development for some of the characters are just outright bad.\u001b[24m\n[ \u001b[4mEnglish\u001b[24m -> \u001b[1m日本語\u001b[22m ]\n\n\u001b[4mWhen it is easier to empathize with a minor character that gets kill off in two episodes than it for a major character than there is a major problem in the works.\u001b[24m\n    \u001b[1mメジャーなキャラクターよりも2つのエピソードで殺されたマイナーキャラクターで共感するほうが、作品に大きな問題があるよりも簡単です。\u001b[22m, \u001b[1m作品に大きな問題があるよりも、主要なキャラクターのためのそれよりも2つのエピソードでオフに殺す取得マイナーなキャラクターに共感することが容易であるとき。\u001b[22m\n\u001b[4mThe character development for some of the characters are just outright bad.\u001b[24m\n    \u001b[1m一部のキャラクターのキャラクター開発は、大したことはありません。\u001b[22m, \u001b[1m文字の一部の文字の開発はちょうど完全に悪いです。\u001b[22m\n\u001b[1m\u001b[22m\nTwo of the more egregious examples are Zeheart and Kio. For a fair part of the anime, the viewers see Zeheart as a person who struggles between fulfilling Ezelcant's Project Eden and his wishes to lead a normal human life. Though Zeheart seems as though he is willing to go through with fulfilling Project Eden, one can see that he has difficulty ridding the obstacles to the plan namely Asemu and Gundam. Not only that, Zeheart has streak of being a stern but caring commander. Which is why when he blindly submits to Ezelcant after becoming the leader of the Vagan and killing off his subordinates in order to achieve his plan, it ruins his character. This isn't to say that it wasn't a valid way of developing his character but it is a bad way. It contradicts and ruins everything that makes Zeheart who he is up until that point. Even something like Zeheart altering Ezelcant's plan after finding out the truth behind Project Eden would make more sense.\n\n\u001b[1mより深刻な例の2つは、ZeheartとKioです。 アニメのかなりの部分を見ると、視聴者はZeheartを、EzelcantのProject Edenと通常の人間の生活を送ることを希望する人との間で闘う人物と見なします。  ZeheartはProject Edenを実行しているかのように見えますが、AsemuとGundamの障害を取り除くのが難しいことがわかります。 それだけでなく、Zeheartは険しくても気遣う指揮官になっています。 だから彼が計画を達成するためにVaganのリーダーになって部下を殺した後、彼が盲目的にEzelcantに提出すると、彼の性格は失われます。 これは、それが彼の性格を発達させる有効な方法ではないが、それは悪い方法であると言っているわけではない。 それはZeheartを作るすべてを矛盾させ、破棄し、その時点までに彼は立ち上がっている。  Zeheartのようなものでも、Project Edenの背後にある真実を見つけた後で、Ezelcantの計画を変えても意味があります。\u001b[22m\n\u001b[1m(Yori shinkokuna rei no 2tsu wa, Zeheart to Kiodesu. Anime no kanari no bubun o miru to, shichō-sha wa Zeheart o, Ezelcant no Project eden to tsūjō no ningen no seikatsu o okuru koto o kibō suru hito to no ma de tatakau jinbutsu to minashimasu. Zeheart wa Project eden o jikkō shite iru ka no yō ni miemasuga, Asemu to Gundam no shōgai o torinozoku no ga muzukashī koto ga wakarimasu. Sore dakedenaku, Zeheart wa kewashikute mo kidzukau shiki-kan ni natte imasu. Dakara kare ga keikaku o tassei suru tame ni Vagan no rīdā ni natte buka o koroshita nochi, kare ga mōmokuteki ni Ezelcant ni teishutsu suru to, kare no seikaku wa ushinawa remasu. Kore wa, sore ga kare no seikaku o hattatsu sa seru yūkōna hōhōde wa naiga, sore wa warui hōhōdearu to itte iru wakede wanai. Sore wa Zeheart o tsukuru subete o mujun sa se, haki shi, sono jiten made ni kare wa tachiagatte iru. Zeheart no yōna monode mo, Project eden no haigo ni aru shinjitsu o mitsuketa nochi de, Ezelcant no keikaku o kaete mo imi ga arimasu.)\u001b[22m\n\nTranslations of \u001b[4mTwo of the more egregious examples are Zeheart and Kio. For a fair part of the anime, the viewers see Zeheart as a person who struggles between fulfilling Ezelcant's Project Eden and his wishes to lead a normal human life. Though Zeheart seems as though he is willing to go through with fulfilling Project Eden, one can see that he has difficulty ridding the obstacles to the plan namely Asemu and Gundam. Not only that, Zeheart has streak of being a stern but caring commander. Which is why when he blindly submits to Ezelcant after becoming the leader of the Vagan and killing off his subordinates in order to achieve his plan, it ruins his character. This isn't to say that it wasn't a valid way of developing his character but it is a bad way. It contradicts and ruins everything that makes Zeheart who he is up until that point. Even something like Zeheart altering Ezelcant's plan after finding out the truth behind Project Eden would make more sense.\u001b[24m\n[ \u001b[4mEnglish\u001b[24m -> \u001b[1m日本語\u001b[22m ]\n\n\u001b[4mTwo of the more egregious examples are Zeheart and Kio.\u001b[24m\n    \u001b[1mより深刻な例の2つは、ZeheartとKioです。\u001b[22m, \u001b[1mもっとひどい例の二つはZeheartと畿央です。\u001b[22m\n\u001b[4mFor a fair part of the anime, the viewers see Zeheart as a person who struggles between fulfilling Ezelcant's Project Eden and his wishes to lead a normal human life.\u001b[24m\n    \u001b[1mアニメのかなりの部分を見ると、視聴者はZeheartを、EzelcantのProject Edenと通常の人間の生活を送ることを希望する人との間で闘う人物と見なします。\u001b[22m, \u001b[1mアニメの公正な部分については、視聴者は、正常なヒトの生活をEzelcantのプロジェクトエデンと彼の願いを果たすの間闘争者としてZeheartを参照してください。\u001b[22m\n\u001b[4mThough Zeheart seems as though he is willing to go through with fulfilling Project Eden, one can see that he has difficulty ridding the obstacles to the plan namely Asemu and Gundam.\u001b[24m\n    \u001b[1mZeheartはProject Edenを実行しているかのように見えますが、AsemuとGundamの障害を取り除くのが難しいことがわかります。\u001b[22m, \u001b[1m彼はプロジェクトエデンを果たして通過する意思があるかのようにZeheartはそうけれども、一つは彼が計画すなわちAsemuとガンダムへの障害をなくし難しさを持っていることがわかります。\u001b[22m\n\u001b[4mNot only that, Zeheart has streak of being a stern but caring commander.\u001b[24m\n    \u001b[1mそれだけでなく、Zeheartは険しくても気遣う指揮官になっています。\u001b[22m, \u001b[1mそれだけでなく、Zeheartは船尾が、思いやりのある指揮官であることの連勝を持っています。\u001b[22m\n\u001b[4mWhich is why when he blindly submits to Ezelcant after becoming the leader of the Vagan and killing off his subordinates in order to achieve his plan, it ruins his character.\u001b[24m\n    \u001b[1mだから彼が計画を達成するためにVaganのリーダーになって部下を殺した後、彼が盲目的にEzelcantに提出すると、彼の性格は失われます。\u001b[22m, \u001b[1mこれは、彼は盲目的にVaganのリーダーになると彼の計画を達成するために、彼の部下を殺した後Ezelcantに送信したとき、それは彼の性格遺跡理由です。\u001b[22m\n\u001b[4mThis isn't to say that it wasn't a valid way of developing his character but it is a bad way.\u001b[24m\n    \u001b[1mこれは、それが彼の性格を発達させる有効な方法ではないが、それは悪い方法であると言っているわけではない。\u001b[22m, \u001b[1mこれは、彼の性格を開発する有効な方法ではありませんでしたが、それは悪い方法であると言っているわけではありません。\u001b[22m\n\u001b[4mIt contradicts and ruins everything that makes Zeheart who he is up until that point.\u001b[24m\n    \u001b[1mそれはZeheartを作るすべてを矛盾させ、破棄し、その時点までに彼は立ち上がっている。\u001b[22m, \u001b[1mこれは、矛盾とZeheartは彼がその時点までで行い、すべてを台無しに。\u001b[22m\n\u001b[4mEven something like Zeheart altering Ezelcant's plan after finding out the truth behind Project Eden would make more sense.\u001b[24m\n    \u001b[1mZeheartのようなものでも、Project Edenの背後にある真実を見つけた後で、Ezelcantの計画を変えても意味があります。\u001b[22m, \u001b[1mより理にかなってプロジェクトエデンの背後にある真実を発見した後Ezelcantの計画を変更することZeheartようにも何か。\u001b[22m\n\u001b[1m\u001b[22m\n\u001b[1m\u001b[22m\nAs for Kio, he never really got character development to begin with. He reaches that phase of naiveté where he 'wants to protect everyone' and 'stop the fighting'. This is fair considering he was exposed to the more humane side of the Vagan but he never grows out of that phase. He desperately tries to stop the fighting for the better part of the last arc and doesn't stop after seeing that his attempts are fruitless and the deaths of his fellow soldiers. Kio almost becomes this wishy-washy Kira clone who constantly spews about peace, but never actually does enough to amount to anything.\n\n\u001b[1mKioに関しては、彼は本当に始まったキャラクターの開発を本当に得たことはありません。 彼は「誰もが守りたい」「戦いをやめよう」といった欲求不満の段階に達しています。 これは彼がVaganのより人道的な側面にさらされていたと考えれば公正ですが、彼はその段階から成長することはありません。 彼は最後の弧のより良い部分のために戦いを止めようと絶望的に努力しており、彼の試みが無意味であり、彼の仲間の死者を見た後も止まない。  Kioは、いつも平和について噴出しているが、実際には何にもなることはない。\u001b[22m\n\u001b[1m(Kio ni kanshite wa, kare wa hontōni hajimatta kyarakutā no kaihatsu o hontōni eta koto wa arimasen. Kare wa `daremoga mamoritai'`tatakai o yameyou' to itta yokkyū fuman no dankai ni tasshite imasu. Kore wa kare ga Vagan no yori jindōtekina sokumen ni sarasa rete ita to kangaereba kōseidesuga, kare wa sono dankai kara seichō suru koto wa arimasen. Kare wa saigo no ko no yoriyoi bubun no tame ni tatakai o tomeyou to zetsubō-teki ni doryoku shite ori, kare no kokoromi ga muimideari, kare no nakama no shisha o mita nochi mo yamanai. Kio wa, itsumo heiwa ni tsuite funshutsu shite iruga, jissai ni wa nani ni mo naru koto wanai.)\u001b[22m\n\nTranslations of \u001b[4mAs for Kio, he never really got character development to begin with. He reaches that phase of naiveté where he 'wants to protect everyone' and 'stop the fighting'. This is fair considering he was exposed to the more humane side of the Vagan but he never grows out of that phase. He desperately tries to stop the fighting for the better part of the last arc and doesn't stop after seeing that his attempts are fruitless and the deaths of his fellow soldiers. Kio almost becomes this wishy-washy Kira clone who constantly spews about peace, but never actually does enough to amount to anything.\u001b[24m\n[ \u001b[4mEnglish\u001b[24m -> \u001b[1m日本語\u001b[22m ]\n\n\u001b[4mAs for Kio, he never really got character development to begin with.\u001b[24m\n    \u001b[1mKioに関しては、彼は本当に始まったキャラクターの開発を本当に得たことはありません。\u001b[22m, \u001b[1m畿央については、彼は本当にで開始する文字の開発をやったことがなかったです。\u001b[22m\n\u001b[4mHe reaches that phase of naiveté where he 'wants to protect everyone' and 'stop the fighting'.\u001b[24m\n    \u001b[1m彼は「誰もが守りたい」「戦いをやめよう」といった欲求不満の段階に達しています。\u001b[22m, \u001b[1m彼は「すべての人を保護したい 'と'戦闘を停止する」無邪気のその段階に到達しました。\u001b[22m\n\u001b[4mThis is fair considering he was exposed to the more humane side of the Vagan but he never grows out of that phase.\u001b[24m\n    \u001b[1mこれは彼がVaganのより人道的な側面にさらされていたと考えれば公正ですが、彼はその段階から成長することはありません。\u001b[22m, \u001b[1mこれは彼がVaganのより人間的な側面に露出したが、彼はその位相がずれて成長したことがない考慮公正です。\u001b[22m\n\u001b[4mHe desperately tries to stop the fighting for the better part of the last arc and doesn't stop after seeing that his attempts are fruitless and the deaths of his fellow soldiers.\u001b[24m\n    \u001b[1m彼は最後の弧のより良い部分のために戦いを止めようと絶望的に努力しており、彼の試みが無意味であり、彼の仲間の死者を見た後も止まない。\u001b[22m, \u001b[1m彼は必死に最後の円弧のよりよい部分のための戦いを停止しようと彼の試みは無益と彼の仲間の兵士の死であることを見た後に停止しません。\u001b[22m\n\u001b[4mKio almost becomes this wishy-washy Kira clone who constantly spews about peace, but never actually does enough to amount to anything.\u001b[24m\n    \u001b[1mKioは、いつも平和について噴出しているが、実際には何にもなることはない。\u001b[22m, \u001b[1m畿央はほとんど常に平和を吐き出すこのなよなよキラクローンになりますが、決して実際には何に達するのに十分を行います。\u001b[22m\n\u001b[1m\u001b[22m\nCompare Kio to Uso from Mobile Suit Victory Gundam. Much like Kio, Uso is constantly bombarded with the realities of war and seen deaths of those close to him. There is a small time frame in which he comes to the same conclusions as Kio, but after seeing that the only way to stop the fighting is to fight and forcibly end the war, Uso's character develops. Uso values peace but understands that he has to fight for it and rather than enforcing his views on everyone he uses it as a rallying call to motivate himself. This example could have been a direction in which Kio could have been developed except it never happened.\n\n\u001b[1m機動戦士勝利のガンダムからKioとUsoを比較してください。 キオのように、ウソは常に戦争の現実に砲撃され、彼に近い人の死を見ました。 彼はKioと同じ結論になる小さな時間枠がありますが、戦いを止める唯一の方法は戦争と強制的に戦争を終わらせることだと見て、Usoの性格が発達します。  Usoは平和を重んじますが、彼はそれを求めて戦う必要があると理解し、自分を動機付けるための呼びかけとしてそれを使用するすべての人に彼の見解を強制するのではなく、 この例は、決して起こらなかったことを除いてKioが開発された可能性のある方向性であった可能性があります。\u001b[22m\n\u001b[1m(Kidō senshi shōri no Gandamu kara Kio to Uso o hikaku shite kudasai. Kio no yō ni, uso wa tsuneni sensō no genjitsu ni hōgeki sa re, kare ni chikai hito no shi o mimashita. Kare wa Kio to onaji ketsuron ni naru chīsana jikan-waku ga arimasuga, tatakai o tomeru yuiitsu no hōhō wa sensō to kyōsei-teki ni sensō o owara seru kotoda to mite, Uso no seikaku ga hattatsu shimasu. Uso wa heiwa o omonjimasuga, kare wa sore o motomete tatakau hitsuyō ga aru to rikai shi, jibun o dōkizukeru tame no yobikake to shite sore o shiyō suru subete no hito ni kare no kenkai o kyōsei suru node wa naku, kono-rei wa, kesshite okoranakatta koto o nozoite Kio ga kaihatsu sa reta kanōsei no aru hōkō-seideatta kanōsei ga arimasu.)\u001b[22m\n\nTranslations of \u001b[4mCompare Kio to Uso from Mobile Suit Victory Gundam. Much like Kio, Uso is constantly bombarded with the realities of war and seen deaths of those close to him. There is a small time frame in which he comes to the same conclusions as Kio, but after seeing that the only way to stop the fighting is to fight and forcibly end the war, Uso's character develops. Uso values peace but understands that he has to fight for it and rather than enforcing his views on everyone he uses it as a rallying call to motivate himself. This example could have been a direction in which Kio could have been developed except it never happened.\u001b[24m\n[ \u001b[4mEnglish\u001b[24m -> \u001b[1m日本語\u001b[22m ]\n\n\u001b[4mCompare Kio to Uso from Mobile Suit Victory Gundam.\u001b[24m\n    \u001b[1m機動戦士勝利のガンダムからKioとUsoを比較してください。\u001b[22m, \u001b[1m機動戦士Vガンダムから嘘に畿央の比較。\u001b[22m\n\u001b[4mMuch like Kio, Uso is constantly bombarded with the realities of war and seen deaths of those close to him.\u001b[24m\n    \u001b[1mキオのように、ウソは常に戦争の現実に砲撃され、彼に近い人の死を見ました。\u001b[22m, \u001b[1m多く畿央のように、嘘は常に戦争の現実が殺到し、彼に近い人の死亡が見られています。\u001b[22m\n\u001b[4mThere is a small time frame in which he comes to the same conclusions as Kio, but after seeing that the only way to stop the fighting is to fight and forcibly end the war, Uso's character develops.\u001b[24m\n    \u001b[1m彼はKioと同じ結論になる小さな時間枠がありますが、戦いを止める唯一の方法は戦争と強制的に戦争を終わらせることだと見て、Usoの性格が発達します。\u001b[22m, \u001b[1m彼は畿央と同じ結論になるが、戦闘を停止する唯一の方法は戦うと強制的に戦争を終わらせるためにあることを見た後、嘘の文字が発達した小さな時間枠があります。\u001b[22m\n\u001b[4mUso values peace but understands that he has to fight for it and rather than enforcing his views on everyone he uses it as a rallying call to motivate himself.\u001b[24m\n    \u001b[1mUsoは平和を重んじますが、彼はそれを求めて戦う必要があると理解し、自分を動機付けるための呼びかけとしてそれを使用するすべての人に彼の見解を強制するのではなく、\u001b[22m, \u001b[1m嘘は平和値が、彼はそれのために戦うというより、彼は自分自身をやる気にさせるラリーコールとしてそれを使用するすべての人に彼の見解を施行しなければならないことを理解しています。\u001b[22m\n\u001b[4mThis example could have been a direction in which Kio could have been developed except it never happened.\u001b[24m\n    \u001b[1mこの例は、決して起こらなかったことを除いてKioが開発された可能性のある方向性であった可能性があります。\u001b[22m, \u001b[1mこの例では、それが起こったことがない以外は畿央が開発されている可能性がある方向だったかもしれません。\u001b[22m\n\u001b[1m\u001b[22m\nThese two are only the more prominent examples but there are other gripes to be had. One can make an argument that Emily was a poorly done version of a concerned friend - almost bordering on possessive and obsessive. Yurin is the star-crossed lover of Flit who is so one dimensional it seems as though she was only added in as a love interest and to fan Flit's hatred of the Vagan.\n\n\u001b[1mこれらの2つはより顕著な例に過ぎませんが、他の悩みがあります。 エミリーは、友情的で強迫観念に近い、関係する友人の貧弱なバージョンであったという主張をすることができます。 ユリインは、フラットの恋人で、一次元なので、彼女は愛の関心事として追加されただけで、フリートのヴァーガンの憎しみを扇動するように見えます。\u001b[22m\n\u001b[1m(Korera no 2tsu wa yori kenchona rei ni sugimasenga, hoka no nayami ga arimasu. Emirī wa, yūjō-tekide kyōhaku kan'nen ni chikai, kankei suru yūjin no hinjakuna bājondeatta to iu shuchō o suru koto ga dekimasu. Yuri in wa, furatto no koibito de, ichi-jigen'nanode, kanojo wa ai no kanshinji to shite tsuika sa reta dake de, furīto no vu~āgan no nikushimi o sendō suru yō ni miemasu.)\u001b[22m\n\nTranslations of \u001b[4mThese two are only the more prominent examples but there are other gripes to be had. One can make an argument that Emily was a poorly done version of a concerned friend - almost bordering on possessive and obsessive. Yurin is the star-crossed lover of Flit who is so one dimensional it seems as though she was only added in as a love interest and to fan Flit's hatred of the Vagan.\u001b[24m\n[ \u001b[4mEnglish\u001b[24m -> \u001b[1m日本語\u001b[22m ]\n\n\u001b[4mThese two are only the more prominent examples but there are other gripes to be had.\u001b[24m\n    \u001b[1mこれらの2つはより顕著な例に過ぎませんが、他の悩みがあります。\u001b[22m, \u001b[1mこれら二つは、より顕著な例ですが、持っていたことがために、他の不満があります。\u001b[22m\n\u001b[4mOne can make an argument that Emily was a poorly done version of a concerned friend - almost bordering on possessive and obsessive.\u001b[24m\n    \u001b[1mエミリーは、友情的で強迫観念に近い、関係する友人の貧弱なバージョンであったという主張をすることができます。\u001b[22m, \u001b[1mほとんど所有と強迫観念を境に - 一つは、エミリーが関係友人の不十分行っバージョンだった議論をすることができます。\u001b[22m\n\u001b[4mYurin is the star-crossed lover of Flit who is so one dimensional it seems as though she was only added in as a love interest and to fan Flit's hatred of the Vagan.\u001b[24m\n    \u001b[1mユリインは、フラットの恋人で、一次元なので、彼女は愛の関心事として追加されただけで、フリートのヴァーガンの憎しみを扇動するように見えます。\u001b[22m, \u001b[1mゆりんは、彼女が唯一の愛興味としてとVaganのファンフリットの憎しみに追加されたかのようにそれはそうそう1次元である夜逃げの薄幸の恋人です。\u001b[22m\n\u001b[1m\u001b[22m\nSome interesting characters seemingly fall off near the end as it seem that the directing and writing team struggled to make a consistent character and resolve plot points. It was interesting (at least in the Gundam franchise) to see a character so driven by revenge and hatred and have it affect every decision he ever makes. And yet he softens up at the end just to tie up the plot. Again this makes for extremely bad character development.\n\n\u001b[1mディレクティングとライティングのチームが一貫したキャラクターを作ってプロットポイントを解決しようと苦労しているように見えるので、面白いキャラクターが終わり近くに見えてしまうようです。 彼は復讐と憎しみに追い込まれたキャラクターを見て、彼が今までに行ったあらゆる決定に影響を与えるのは面白かった（少なくともガンダムフランチャイズでは）。 それでも、彼はプロットを結びつけるために最後に柔らかくなります。 これもまた、非常に悪いキャラクター開発の原因となります。\u001b[22m\n\u001b[1m(Direkutingu to raitingu no chīmu ga ikkan shita kyarakutā o tsukutte purotto pointo o kaiketsu shiyou to kurō shite iru yō ni mieru node, omoshiroi kyarakutā ga owari chikaku ni miete shimau yōdesu. Kare wa fukushū to nikushimi ni oikoma reta kyarakutā o mite, kare ga ima made ni itta arayuru kettei ni eikyōwoataeru no wa omoshirokatta (sukunakutomo gandamufuranchaizude wa). Soredemo, kare wa purotto o musubitsukeru tame ni saigo ni yawarakaku narimasu. Kore mo mata, hijō ni warui kyarakutā kaihatsu no gen'in to narimasu.)\u001b[22m\n\nTranslations of \u001b[4mSome interesting characters seemingly fall off near the end as it seem that the directing and writing team struggled to make a consistent character and resolve plot points. It was interesting (at least in the Gundam franchise) to see a character so driven by revenge and hatred and have it affect every decision he ever makes. And yet he softens up at the end just to tie up the plot. Again this makes for extremely bad character development.\u001b[24m\n[ \u001b[4mEnglish\u001b[24m -> \u001b[1m日本語\u001b[22m ]\n\n\u001b[4mSome interesting characters seemingly fall off near the end as it seem that the directing and writing team struggled to make a consistent character and resolve plot points.\u001b[24m\n    \u001b[1mディレクティングとライティングのチームが一貫したキャラクターを作ってプロットポイントを解決しようと苦労しているように見えるので、面白いキャラクターが終わり近くに見えてしまうようです。\u001b[22m, \u001b[1m演出やライティングチームが一貫した文字を作り、プロット点を解決するために苦労していることを見えるようにいくつかの興味深い文字は、一見終わり近くに落ちます。\u001b[22m\n\u001b[4mIt was interesting (at least in the Gundam franchise) to see a character so driven by revenge and hatred and have it affect every decision he ever makes.\u001b[24m\n    \u001b[1m彼は復讐と憎しみに追い込まれたキャラクターを見て、彼が今までに行ったあらゆる決定に影響を与えるのは面白かった（少なくともガンダムフランチャイズでは）。\u001b[22m, \u001b[1mそれはとても復讐と憎悪によって駆動される文字を見て、それは彼が今までになり、すべての意思決定に影響を与える持っている（少なくとも、ガンダムのフランチャイズに）面白かったです。\u001b[22m\n\u001b[4mAnd yet he softens up at the end just to tie up the plot.\u001b[24m\n    \u001b[1mそれでも、彼はプロットを結びつけるために最後に柔らかくなります。\u001b[22m, \u001b[1mそして、まだ彼はただプロットを結ぶために終わりに軟化します。\u001b[22m\n\u001b[4mAgain this makes for extremely bad character development.\u001b[24m\n    \u001b[1mこれもまた、非常に悪いキャラクター開発の原因となります。\u001b[22m, \u001b[1m再び、これは非常に悪いキャラクターの成長のためになります。\u001b[22m\n\u001b[1m\u001b[22m\nAll of these characters could have been used to make the anime slightly better had they been better developed.\n\n\u001b[1mこれらのキャラクタはすべて、アニメがより良く開発された場合に、アニメを少し上手にするために使用されていた可能性があります。\u001b[22m\n\u001b[1m(Korera no kyarakuta wa subete, anime ga yori yoku kaihatsu sa reta baai ni, anime o sukoshi jōzu ni suru tame ni shiyō sa rete ita kanōsei ga arimasu.)\u001b[22m\n\nTranslations of \u001b[4mAll of these characters could have been used to make the anime slightly better had they been better developed.\u001b[24m\n[ \u001b[4mEnglish\u001b[24m -> \u001b[1m日本語\u001b[22m ]\n\n\u001b[4mAll of these characters could have been used to make the anime slightly better had they been better developed.\u001b[24m\n    \u001b[1mこれらのキャラクタはすべて、アニメがより良く開発された場合に、アニメを少し上手にするために使用されていた可能性があります。\u001b[22m, \u001b[1m彼らはより良い開発されたこれらの文字はすべて、アニメがわずかに改善するために使用されてきた可能性があります。\u001b[22m\n\u001b[1m\u001b[22m\nOverall Impression: 6\n\n\u001b[1m全体的な印象：6\u001b[22m\n\u001b[1m(Zentai-tekina inshō: 6)\u001b[22m\n\nTranslations of \u001b[4mOverall Impression: 6\u001b[24m\n[ \u001b[4mEnglish\u001b[24m -> \u001b[1m日本語\u001b[22m ]\n\n\u001b[4mOverall Impression: 6\u001b[24m\n    \u001b[1m全体的な印象：6\u001b[22m, \u001b[1m総合印象：6\u001b[22m\n\u001b[1m\u001b[22m\nWas it bad as everyone made it out to be? Not exactly. Were there parts that really annoyed the hell out of me and made me feel like dropping this anime all together? You betcha. As a Gundam fan I wasn't as disappointed as I was with the fanfic plot that is Gundam Seed Destiny. But that's not really saying much. There was an opportunity that the Gundam franchise and Sunrise could have capitalize but due to shoddy directing and writing a lot of it went to waste.\n\n\u001b[1m誰もがそれを作るように悪いことでしたか？ ではない正確に。 実際に私を怒らせて、このアニメを一緒に落とすような気分にさせた部分はありましたか？ もちろんです。 ガンダムのファンとして、私はガンダムシードの運命であるファンフィックプロットと同じように、私は失望していませんでした。 しかし、それはあまり意味がありません。 ガンダムフランチャイズとサンライズが大金を稼ぐ機会がありましたが、いたずらな演出と執筆のために多くのことが無駄になりました。\u001b[22m\n\u001b[1m(Daremoga sore o tsukuru yō ni warui kotodeshita ka?De wanai seikaku ni. Jissai ni watashi o okora sete, kono anime o issho ni otosu yōna kibun ni sa seta bubun wa arimashita ka? Mochirondesu. Gandamu no fan to shite, watashi wa gandamushīdo no unmeidearu fanfikkupurotto to onajiyōni, watashi wa shitsubō shite imasendeshita. Shikashi, sore wa amari imi ga arimasen. Gandamufuranchaizu to sanraizu ga taikin o kasegu kikai ga arimashitaga, itazurana enshutsu to shippitsu no tame ni ōku no koto ga muda ni narimashita.)\u001b[22m\n\nTranslations of \u001b[4mWas it bad as everyone made it out to be? Not exactly. Were there parts that really annoyed the hell out of me and made me feel like dropping this anime all together? You betcha. As a Gundam fan I wasn't as disappointed as I was with the fanfic plot that is Gundam Seed Destiny. But that's not really saying much. There was an opportunity that the Gundam franchise and Sunrise could have capitalize but due to shoddy directing and writing a lot of it went to waste.\u001b[24m\n[ \u001b[4mEnglish\u001b[24m -> \u001b[1m日本語\u001b[22m ]\n\n\u001b[4mWas it bad as everyone made it out to be?\u001b[24m\n    \u001b[1m誰もがそれを作るように悪いことでしたか？\u001b[22m, \u001b[1m誰もがするそれを作ったとして、それが悪かったですか？\u001b[22m\n\u001b[4mNot exactly.\u001b[24m\n    \u001b[1mではない正確に。\u001b[22m, \u001b[1m正確ではない。\u001b[22m, \u001b[1mそういうわけでもありません。\u001b[22m\n\u001b[4mWere there parts that really annoyed the hell out of me and made me feel like dropping this anime all together?\u001b[24m\n    \u001b[1m実際に私を怒らせて、このアニメを一緒に落とすような気分にさせた部分はありましたか？\u001b[22m, \u001b[1m本当に私の地獄を悩ませ、私はすべて一緒にこのアニメを落とすように感じる作られた部品はありましたか？\u001b[22m\n\u001b[4mYou betcha.\u001b[24m\n    \u001b[1mもちろんです。\u001b[22m, \u001b[1mあなたはベッカです。\u001b[22m, \u001b[1mもちろんです。。\u001b[22m\n\u001b[4mAs a Gundam fan I wasn't as disappointed as I was with the fanfic plot that is Gundam Seed Destiny.\u001b[24m\n    \u001b[1mガンダムのファンとして、私はガンダムシードの運命であるファンフィックプロットと同じように、私は失望していませんでした。\u001b[22m, \u001b[1mガンダムファンとして、私は私がガンダムSEEDデスティニーあるfanficプロットしていたほど失望しませんでした。\u001b[22m\n\u001b[4mBut that's not really saying much.\u001b[24m\n    \u001b[1mしかし、それはあまり意味がありません。\u001b[22m, \u001b[1mしかし、それは本当に多くを言っていません。\u001b[22m\n\u001b[4mThere was an opportunity that the Gundam franchise and Sunrise could have capitalize but due to shoddy directing and writing a lot of it went to waste.\u001b[24m\n    \u001b[1mガンダムフランチャイズとサンライズが大金を稼ぐ機会がありましたが、いたずらな演出と執筆のために多くのことが無駄になりました。\u001b[22m, \u001b[1mガンダムのフランチャイズと日の出が大文字に持つことができるが、見掛け倒しの演出のために、それをたくさん書いては無駄になったこと機会がありました。\u001b[22m\n\u001b[1m\u001b[22m\nFor the average watcher, they may get some mild enjoyment out of this. Even then it may feel taxing and boring at times. It stands as a mediocre Gundam series and will always be remembered as a mediocre Gundam series.\n\n\u001b[1m平均的なウォッチャーのために、彼らはこれからいくらか軽い楽しみを得るかもしれません。 それでも、時には、それは時には過度の負担と退屈を感じるかもしれません。 それは普通のガンダムシリーズとして立派で、ガンダムシリーズとして常に記憶されています。\u001b[22m\n\u001b[1m(Heikin-tekina u~otchā no tame ni, karera wa korekara ikuraka karui tanoshimi o eru kamo shiremasen. Soredemo, tokiniha, sore wa tokiniha kado no futan to taikutsu o kanjiru kamo shiremasen. Sore wa futsū no gandamushirīzu to shite rippade, gandamushirīzu to shite tsuneni kioku sa rete imasu.)\u001b[22m\n\nTranslations of \u001b[4mFor the average watcher, they may get some mild enjoyment out of this. Even then it may feel taxing and boring at times. It stands as a mediocre Gundam series and will always be remembered as a mediocre Gundam series.\u001b[24m\n[ \u001b[4mEnglish\u001b[24m -> \u001b[1m日本語\u001b[22m ]\n\n\u001b[4mFor the average watcher, they may get some mild enjoyment out of this.\u001b[24m\n    \u001b[1m平均的なウォッチャーのために、彼らはこれからいくらか軽い楽しみを得るかもしれません。\u001b[22m, \u001b[1m平均ウォッチャーのために、彼らはこのうちいくつかの穏やかな楽しみを得ることができます。\u001b[22m\n\u001b[4mEven then it may feel taxing and boring at times.\u001b[24m\n    \u001b[1mそれでも、時には、それは時には過度の負担と退屈を感じるかもしれません。\u001b[22m, \u001b[1mでもそれは時間に課税し、退屈を感じることがあります。\u001b[22m\n\u001b[4mIt stands as a mediocre Gundam series and will always be remembered as a mediocre Gundam series.\u001b[24m\n    \u001b[1mそれは普通のガンダムシリーズとして立派で、ガンダムシリーズとして常に記憶されています。\u001b[22m, \u001b[1mそれは、平凡なガンダムシリーズとして立って、常に平凡ガンダムシリーズとして記憶されるだろう。\u001b[22m\n\u001b[1m\u001b[22m\n\u001b[1m\u001b[22m\n\u001b[1m\u001b[22m"
  },
  {
    "title": "Mobile_Suit_Gundam_AGE",
    "id": "10808",
    "url": "https://myanimelist.net/anime/10808/Mobile_Suit_Gundam_AGE",
    "user": "pika2000",
    "profile": "/profile/pika2000/reviews",
    "pages": "2",
    "number": "3",
    "link": "/reviews.php?id=61595",
    "jp": "--- | --- | ---\n全体的な|  7\n--- | ---\nストーリー|  6\nアニメーション|  8\nサウンド|  8\nキャラクター|  6\n|  6\n\nガンダム時代、ガンダムフランチャイズの最新作。 主人公の1人ではなく、3世代に3つの異なるガンダムパイロットが連続しています。 素晴らしいコンセプトのように聞こえるよね？\n\nそれは、当初です。 しかし今、第31話では、すでに第3のパイロットにいます。 それは非常にばらばらです。 さらに悪いことに、あなたがAsemuの開発を見始めた時、彼らはアークを終了し、第3のものを開始しました。 サポートキャラクターから始めてはいけません。 メインパイロットと別の1秒のメインパイロット以外のパイロットの残りの部分はほとんど役に立たないので、最初にパイロットになることができます。 これは、Asemu / Woolfがすべてをやっている唯一のものであるところで、2番目の弧で増幅されます。 とてもうるさい。 それが問題です。 私はおもちゃを売ることに興味があるので、別のガンダムを速く反復する必要があると確信しています。 代わりに、物語とキャラクターが苦しんでいます。 最初の弧はFlit Asunoで始まりました。 この弧は、実際にはかなり初期のペースですが、物事を速く動かすことは明らかです。 キャラクターの発展はばらばらになりました。  Aseno Asunoとの2番目の弧ではさらに悪いことです。 私は会話の直後、または次のシーンの2つまたはそれ以降のものを文字通りに見ることを意味します。\n\n私はあなたが既に別の場所でその物語を読んでいると確信しているので、私はそれをスキップします。 しかし、私はファンのサービスを指摘したいと思います。 私は彼らがファンサービスであるのか、作家が怠け者であるのかは分かりません。  AGEガンダムのデザイン、多くの場面などは、UCシリーズ、AGE-1を元のガンダムに、AGE-2をゼータガンダムに、そしてAGE-3をガンダムZZにミラーリングします。 シーンの類似点については、非常に明白な第1弧のフィナーレを見てください。\n\nメカアートは素晴らしいです。 あなたは何を期待していますか？ それはサンライズです。 一方、文字は簡略化されているように見えるか、あるいは「育てられた」と思われる。 それは間違いなくOOではありませんが、実際には古いガンダムシリーズに戻っています。 大したことではありませんが、ばらばらのペーシングは全体的な楽しみを助けません。\n\n結局のところ、それはいいガンダムシリーズです。 私はそれがシンプルなガンダムのデザイン（SEEDと比較して）を見て爽快であることを意味し、いくつかのシーンはUCガンダムシリーズからの懐かしさをもたらします。 それでも、ストーリーは特にOOの後に単純すぎるように見え、ペーシングはちょっと面倒です。 私たちがこれをすばやく乗り越えて進むことができるようにしましょう。",
    "notes": "---|---|---\n\n\u001b[1m--- | --- | ---\u001b[22m\n\u001b[1m(-- - | -- - | -- -)\u001b[22m\n\nTranslations of \u001b[4m---|---|---\u001b[24m\n[ \u001b[4mEnglish\u001b[24m -> \u001b[1m日本語\u001b[22m ]\n\n\u001b[4m---|---|---\u001b[24m\n    \u001b[1m--- | --- | ---\u001b[22m\nOverall | 7\n\n\u001b[1m全体的な|  7\u001b[22m\n\u001b[1m(Zentai-tekina | 7)\u001b[22m\n\nTranslations of \u001b[4mOverall | 7\u001b[24m\n[ \u001b[4mEnglish\u001b[24m -> \u001b[1m日本語\u001b[22m ]\n\n\u001b[4mOverall |\u001b[24m\n    \u001b[1m全体的な|\u001b[22m, \u001b[1m総合的な|\u001b[22m\n\u001b[4m7\u001b[24m\n    \u001b[1m7\u001b[22m\n---|---\n\n\u001b[1m--- | ---\u001b[22m\n\u001b[1m(-- - | -- -)\u001b[22m\n\nTranslations of \u001b[4m---|---\u001b[24m\n[ \u001b[4mEnglish\u001b[24m -> \u001b[1m日本語\u001b[22m ]\n\n\u001b[4m---|---\u001b[24m\n    \u001b[1m--- | ---\u001b[22m\nStory | 6\n\n\u001b[1mストーリー|  6\u001b[22m\n\u001b[1m(Sutōrī | 6)\u001b[22m\n\nTranslations of \u001b[4mStory | 6\u001b[24m\n[ \u001b[4mEnglish\u001b[24m -> \u001b[1m日本語\u001b[22m ]\n\n\u001b[4mStory |\u001b[24m\n    \u001b[1mストーリー|\u001b[22m\n\u001b[4m6\u001b[24m\n    \u001b[1m6\u001b[22m\nAnimation | 8\n\n\u001b[1mアニメーション|  8\u001b[22m\n\u001b[1m(Animēshon | 8)\u001b[22m\n\nTranslations of \u001b[4mAnimation | 8\u001b[24m\n[ \u001b[4mEnglish\u001b[24m -> \u001b[1m日本語\u001b[22m ]\n\n\u001b[4mAnimation |\u001b[24m\n    \u001b[1mアニメーション|\u001b[22m\n\u001b[4m8\u001b[24m\n    \u001b[1m8\u001b[22m\nSound | 8\n\n\u001b[1mサウンド|  8\u001b[22m\n\u001b[1m(Saundo | 8)\u001b[22m\n\nTranslations of \u001b[4mSound | 8\u001b[24m\n[ \u001b[4mEnglish\u001b[24m -> \u001b[1m日本語\u001b[22m ]\n\n\u001b[4mSound |\u001b[24m\n    \u001b[1mサウンド|\u001b[22m\n\u001b[4m8\u001b[24m\n    \u001b[1m8\u001b[22m\nCharacter | 6\n\n\u001b[1mキャラクター|  6\u001b[22m\n\u001b[1m(Kyarakutā | 6)\u001b[22m\n\nTranslations of \u001b[4mCharacter | 6\u001b[24m\n[ \u001b[4mEnglish\u001b[24m -> \u001b[1m日本語\u001b[22m ]\n\n\u001b[4mCharacter |\u001b[24m\n    \u001b[1mキャラクター|\u001b[22m, \u001b[1m文字|\u001b[22m\n\u001b[4m6\u001b[24m\n    \u001b[1m6\u001b[22m\nEnjoyment | 6\n\n\u001b[1m|  6\u001b[22m\n\u001b[1m(| 6)\u001b[22m\n\nTranslations of \u001b[4mEnjoyment | 6\u001b[24m\n[ \u001b[4mEnglish\u001b[24m -> \u001b[1m日本語\u001b[22m ]\n\n\u001b[4mEnjoyment |\u001b[24m\n    \u001b[1m|\u001b[22m, \u001b[1m楽しさ|\u001b[22m\n\u001b[4m6\u001b[24m\n    \u001b[1m6\u001b[22m\n\u001b[1m\u001b[22m\nGundam Age, the latest installment of the Gundam franchise. Instead of just one main character, the story is set into 3 generations, with 3 different gundam pilots over a continuing timeline. Sounds like a great concept, right?\n\n\u001b[1mガンダム時代、ガンダムフランチャイズの最新作。 主人公の1人ではなく、3世代に3つの異なるガンダムパイロットが連続しています。 素晴らしいコンセプトのように聞こえるよね？\u001b[22m\n\u001b[1m(Gandamu jidai, gandamufuranchaizu no saishin-saku. Shujinkō no 1-ride wa naku, 3 sedai ni 3ttsu no kotonaru gandamupairotto ga renzoku shite imasu. Subarashī konseputo no yō ni kikoeru yo ne?)\u001b[22m\n\nTranslations of \u001b[4mGundam Age, the latest installment of the Gundam franchise. Instead of just one main character, the story is set into 3 generations, with 3 different gundam pilots over a continuing timeline. Sounds like a great concept, right?\u001b[24m\n[ \u001b[4mEnglish\u001b[24m -> \u001b[1m日本語\u001b[22m ]\n\n\u001b[4mGundam Age, the latest installment of the Gundam franchise.\u001b[24m\n    \u001b[1mガンダム時代、ガンダムフランチャイズの最新作。\u001b[22m, \u001b[1mガンダム年齢、ガンダムのフランチャイズの最新作。\u001b[22m\n\u001b[4mInstead of just one main character, the story is set into 3 generations, with 3 different gundam pilots over a continuing timeline.\u001b[24m\n    \u001b[1m主人公の1人ではなく、3世代に3つの異なるガンダムパイロットが連続しています。\u001b[22m, \u001b[1mちょうど1主人公の代わりに、物語は継続し、タイムライン上で3つの異なるガンダムパイロットで、3世代に設定されています。\u001b[22m\n\u001b[4mSounds like a great concept, right?\u001b[24m\n    \u001b[1m素晴らしいコンセプトのように聞こえるよね？\u001b[22m, \u001b[1m右、偉大な概念のように聞こえますか？\u001b[22m\n\u001b[1m\u001b[22m\nIt is, at first. But then now in episode 31, we are already on the third pilot. It's extremely disjointed. Worse, just when things seem to pick up and you started to see Asemu's development, they ended the arc and started the third one. Don't get me started on the supporting characters. Other than the main pilot and maybe another one second main pilot, the rest of the pilots are pretty much useless, which makes you wonder how they can become pilots in the first place. This is amplified in the second arc to the extreme where Asemu/Woolf are pretty much the only ones doing everything. Very annoying. That's imo is the problem. I'm sure in the interest to sell toys, they need to iterate the different Gundams fast. In return, the story and characters suffer. The first arc started with Flit Asuno. This arc is actually fairly decently paced at first, but it's clear that they want to move things fast. Character development became disjointed. This is even worse on the second arc, with Asemu Asuno. I mean you literally see things turning around just after a dialogue or two or after the next scene, something that should be paced slower imo.\n\n\u001b[1mそれは、当初です。 しかし今、第31話では、すでに第3のパイロットにいます。 それは非常にばらばらです。 さらに悪いことに、あなたがAsemuの開発を見始めた時、彼らは弧を終えて3番目のものを開始しました。 サポートキャラクターから始めてはいけません。 メインパイロットと別の1秒のメインパイロット以外のパイロットの残りの部分はほとんど役に立たないので、最初にパイロットになることができます。 これは、Asemu / Woolfがすべてをやっている唯一のものであるところで、2番目の弧で増幅されます。 とてもうるさい。 それが問題です。 私はおもちゃを売ることに興味があるので、別のガンダムを速く反復する必要があると確信しています。 代わりに、物語とキャラクターが苦しんでいます。 最初の弧はFlit Asunoで始まりました。 この弧は、実際にはかなり初期のペースですが、物事を速く動かすことは明らかです。 キャラクターの発展はばらばらになりました。  Aseno Asunoとの2番目の弧ではさらに悪いことです。 私は会話の直後、または次のシーンの2つまたはそれ以降のものを文字通りに見ることを意味します。\u001b[22m\n\u001b[1m(Sore wa, tōshodesu. Shikashi ima, dai 31-wade wa, sudeni dai 3 no pairotto ni imasu. Sore ga mondaidesu. Watashi wa omocha o uru koto ni kyōmigārunode,-betsu no Gandamu o hayaku hanpuku suruhitsuyōgāru to kakushin shite imasu. Kawari ni, monogatari to kyarakutā ga kurushinde imasu. Saisho no ko wa Flit Asuno de hajimarimashita. Kono ko wa, jissai ni wa kanari shoki no pēsudesuga, monogoto o hayaku ugokasu koto wa akirakadesu. Kyarakutā no hatten wa barabara ni narimashita. Aseno Asuno to no 2-banme no kode wa saraniwaruikotodesu. Watashi wa kaiwa no chokugo, matawa tsugi no shīn no 2tsu matawa sore ikō no mono o mojidōri ni miru koto o imi shimasu. Sore wa hijō ni barabaradesu. Saraniwaruikoto ni, anata ga Asemu no kaihatsu o mi hajimeta toki, karera wa ko o oete 3-banme no mono o kaishi shimashita. Sapōtokyarakutā kara hajimete wa ikemasen. Mein pairotto to betsu no 1-byō no mein pairotto igai no pairotto no nokori no bubun wa hotondo yakunitatanainode, saisho ni pairotto ni naru koto ga dekimasu. Kore wa, Asemu/ Woolf ga subete o yatte iru yuiitsu no monodearu tokoro de, 2-banme no ko de zōfuku sa remasu. Totemo urusai.)\u001b[22m\n\u001b[1m\u001b[22m\nI'm sure you already read the story somewhere else, so I'll skip that. But I do want to point out the fan services. Thing is, I'm not sure to say whether they are fan services, or the writers are lazy. The AGE Gundams design, many scenes, etc mirror pretty much the UC series, AGE-1 to the original Gundam, AGE-2 to Zeta Gundam, and AGE-3 to Gundam ZZ. As for similarities of scenes, just watch the finale of the 1st arc, very obvious.\n\n\u001b[1m私はあなたが既に別の場所でその物語を読んでいると確信しているので、私はそれをスキップします。 しかし、私はファンのサービスを指摘したいと思います。 私は彼らがファンサービスであるのか、作家が怠け者であるのかは分かりません。  AGEガンダムのデザイン、多くの場面などは、UCシリーズ、AGE-1を元のガンダムに、AGE-2をゼータガンダムに、そしてAGE-3をガンダムZZにミラーリングします。 シーンの類似点については、非常に明白な第1弧のフィナーレを見てください。\u001b[22m\n\u001b[1m(Watashi wa anata ga sudeni betsu no basho de sono monogatari o yonde iru to kakushin shite irunode, watashi wa sore o sukippu shimasu. Shikashi, watashi wa fan no sābisu o shiteki shitai to omoimasu. Watashi wa karera ga fansābisudearu no ka, sakka ga namakemonodearu no ka wa wakarimasen. AGE Gandamu no dezain, ōku no bamen nado wa, UC shirīzu, AGE - 1 o gen no Gandamu ni, AGE - 2 o zētagandamu ni, soshite AGE - 3 o Gandamu ZZ ni mirāringu shimasu. Shīn no ruiji-ten ni tsuite wa, hijō ni meihakuna dai 1 ko no fināre o mite kudasai.)\u001b[22m\n\nTranslations of \u001b[4mI'm sure you already read the story somewhere else, so I'll skip that. But I do want to point out the fan services. Thing is, I'm not sure to say whether they are fan services, or the writers are lazy. The AGE Gundams design, many scenes, etc mirror pretty much the UC series, AGE-1 to the original Gundam, AGE-2 to Zeta Gundam, and AGE-3 to Gundam ZZ. As for similarities of scenes, just watch the finale of the 1st arc, very obvious.\u001b[24m\n[ \u001b[4mEnglish\u001b[24m -> \u001b[1m日本語\u001b[22m ]\n\n\u001b[4mI'm sure you already read the story somewhere else, so I'll skip that.\u001b[24m\n    \u001b[1m私はあなたが既に別の場所でその物語を読んでいると確信しているので、私はそれをスキップします。\u001b[22m, \u001b[1m私はあなたが既にどこか別の物語を読んで確信しているので、私はそれをスキップします。\u001b[22m\n\u001b[4mBut I do want to point out the fan services.\u001b[24m\n    \u001b[1mしかし、私はファンのサービスを指摘したいと思います。\u001b[22m, \u001b[1mしかし、私はファンサービスを指摘したいです。\u001b[22m\n\u001b[4mThing is, I'm not sure to say whether they are fan services, or the writers are lazy.\u001b[24m\n    \u001b[1m私は彼らがファンサービスであるのか、作家が怠け者であるのかは分かりません。\u001b[22m, \u001b[1m事は、私は彼らがファンサービスである、またはライターが怠惰であるかどうかを言うことはわからない、です。\u001b[22m\n\u001b[4mThe AGE Gundams design, many scenes, etc mirror pretty much the UC series, AGE-1 to the original Gundam, AGE-2 to Zeta Gundam, and AGE-3 to Gundam ZZ.\u001b[24m\n    \u001b[1mAGEガンダムのデザイン、多くの場面などは、UCシリーズ、AGE-1を元のガンダムに、AGE-2をゼータガンダムに、そしてAGE-3をガンダムZZにミラーリングします。\u001b[22m, \u001b[1mAGEガンダムデザイン、多くのシーンなどは、ミラーかなりUCシリーズ、AGE-1オリジナルのガンダムに、AGE-2ガンダムZZにゼータガンダム、及びAGE-3へ。\u001b[22m\n\u001b[4mAs for similarities of scenes, just watch the finale of the 1st arc, very obvious.\u001b[24m\n    \u001b[1mシーンの類似点については、非常に明白な第1弧のフィナーレを見てください。\u001b[22m, \u001b[1mシーンの類似性については、ちょうど、非常に明白第一アークのフィナーレを見ます。\u001b[22m\n\u001b[1m\u001b[22m\nThe mecha art is superb. What do you expect? It's Sunrise. The characters, on the other hand, seems to be simplified, or even 'kidified.' It's definitely not OO, but it actually harkens back to the older Gundam series. Not a big deal imo, but the disjointed pacing doesn't help the overall enjoyment.\n\n\u001b[1mメカアートは素晴らしいです。 あなたは何を期待していますか？ それはサンライズです。 一方、文字は簡略化されているように見えるか、あるいは「育てられた」と思われる。 それは間違いなくOOではありませんが、実際には古いガンダムシリーズに憧れています。 大したことではありませんが、ばらばらのペーシングは全体的な楽しみを助けません。\u001b[22m\n\u001b[1m(Mekaāto wa subarashīdesu. Anata wa nani o kitai shite imasu ka? Sore wa sanraizudesu. Ippō, moji wa kanryaku-ka sa rete iru yō ni mieru ka, aruiwa `sodate rareta' to omowa reru. Sore wa machigainaku OOde wa arimasenga, jissai ni wa furui gandamushirīzu ni akogarete imasu. Taishita kotode wa arimasenga, barabara no pēshingu wa zentai-tekina tanoshimi o tasukemasen.)\u001b[22m\n\nTranslations of \u001b[4mThe mecha art is superb. What do you expect? It's Sunrise. The characters, on the other hand, seems to be simplified, or even 'kidified.' It's definitely not OO, but it actually harkens back to the older Gundam series. Not a big deal imo, but the disjointed pacing doesn't help the overall enjoyment.\u001b[24m\n[ \u001b[4mEnglish\u001b[24m -> \u001b[1m日本語\u001b[22m ]\n\n\u001b[4mThe mecha art is superb.\u001b[24m\n    \u001b[1mメカアートは素晴らしいです。\u001b[22m\n\u001b[4mWhat do you expect?\u001b[24m\n    \u001b[1mあなたは何を期待していますか？\u001b[22m, \u001b[1m当たり前だろ。\u001b[22m\n\u001b[4mIt's Sunrise.\u001b[24m\n    \u001b[1mそれはサンライズです。\u001b[22m, \u001b[1mそれは日の出です。\u001b[22m\n\u001b[4mThe characters, on the other hand, seems to be simplified, or even 'kidified.'\u001b[24m\n    \u001b[1m一方、文字は簡略化されているように見えるか、あるいは「育てられた」と思われる。\u001b[22m, \u001b[1m文字は、一方で、簡略化しているように見える、あるいは「kidified」。\u001b[22m\n\u001b[4mIt's definitely not OO, but it actually harkens back to the older Gundam series.\u001b[24m\n    \u001b[1mそれは間違いなくOOではありませんが、実際には古いガンダムシリーズに憧れています。\u001b[22m, \u001b[1mそれは間違いなくオブジェクト指向ではないが、それは実際に古いガンダムシリーズに思い起こさせます。\u001b[22m\n\u001b[4mNot a big deal imo, but the disjointed pacing doesn't help the overall enjoyment.\u001b[24m\n    \u001b[1m大したことではありませんが、ばらばらのペーシングは全体的な楽しみを助けません。\u001b[22m, \u001b[1m大したことは芋が、とりとめのないペーシングは、全体的な楽しみを助けにはならないではありません。\u001b[22m\n\u001b[1m\u001b[22m\nIn the end, it's an okay Gundam series. I mean it's refreshing to see a simpler Gundam design (versus SEED), and some scenes brings nostalgia from the UC Gundam series. Still, the story seems too simplified, especially after OO, and the pacing is just annoying. Let's just hope we can get over this quickly and move on.\n\n\u001b[1m結局のところ、それはいいガンダムシリーズです。 私はそれがシンプルなガンダムのデザイン（SEEDと比較して）を見て爽快であることを意味し、いくつかのシーンはUCガンダムシリーズからの懐かしさをもたらします。 それでも、ストーリーは特にOOの後に単純すぎるように見え、ペーシングはちょっと面倒です。 私たちがこれをすばやく乗り越えて進むことができるようにしましょう。\u001b[22m\n\u001b[1m(Kekkyokunotokoro, sore wa ī gandamushirīzudesu. Watashi wa sore ga shinpuruna Gandamu no dezain (shīdo to hikaku shite) o mite sōkaidearu koto o imi shi, ikutsu ka no shīn wa UC gandamushirīzu kara no natsukashisa o motarashimasu. Soredemo, sutōrī wa tokuni OO no nochi ni tanjun sugiru yō ni mie, pēshingu wa chotto mendōdesu. Watashitachi ga kore o subayaku norikoete susumu koto ga dekiru yō ni shimashou.)\u001b[22m\n\nTranslations of \u001b[4mIn the end, it's an okay Gundam series. I mean it's refreshing to see a simpler Gundam design (versus SEED), and some scenes brings nostalgia from the UC Gundam series. Still, the story seems too simplified, especially after OO, and the pacing is just annoying. Let's just hope we can get over this quickly and move on.\u001b[24m\n[ \u001b[4mEnglish\u001b[24m -> \u001b[1m日本語\u001b[22m ]\n\n\u001b[4mIn the end, it's an okay Gundam series.\u001b[24m\n    \u001b[1m結局のところ、それはいいガンダムシリーズです。\u001b[22m, \u001b[1m最後に、それは大丈夫ガンダムシリーズです。\u001b[22m\n\u001b[4mI mean it's refreshing to see a simpler Gundam design (versus SEED), and some scenes brings nostalgia from the UC Gundam series.\u001b[24m\n    \u001b[1m私はそれがシンプルなガンダムのデザイン（SEEDと比較して）を見て爽快であることを意味し、いくつかのシーンはUCガンダムシリーズからの懐かしさをもたらします。\u001b[22m, \u001b[1m私はそれが（SEED対）より単純なガンダムのデザインを見ることがさわやかだ意味し、いくつかのシーンは、UCガンダムシリーズから郷愁をもたらします。\u001b[22m\n\u001b[4mStill, the story seems too simplified, especially after OO, and the pacing is just annoying.\u001b[24m\n    \u001b[1mそれでも、ストーリーは特にOOの後に単純すぎるように見え、ペーシングはちょっと面倒です。\u001b[22m, \u001b[1mそれでも、物語は特にオブジェクト指向の後、あまりにも単純化されたようで、ペーシングはちょうど迷惑です。\u001b[22m\n\u001b[4mLet's just hope we can get over this quickly and move on.\u001b[24m\n    \u001b[1m私たちがこれをすばやく乗り越えて進むことができるようにしましょう。\u001b[22m, \u001b[1mちょうど私たちはすぐにこの上を取得し、上に移動することができます期待しましょう。\u001b[22m"
  }
]
